{"usage":null,"language":"","entities":[{"type":"ADDRESS","subcategory":"","text":"71-75 Shelton Street, Covent Garden, London, England, WC2H 9JQ","sentiment":{"score":0.0,"label":null},"relevance":0.0,"mentions":[{"text":"71-75 Shelton Street, Covent Garden, London, England, WC2H 9JQ","location":[1777,1839],"confidence":0.92}],"count":0,"confidence":0.92,"usefulness":false,"Metadata":null},{"type":"DATE","subcategory":"DATERANGE","text":"may","sentiment":{"score":0.0,"label":null},"relevance":0.0,"mentions":[{"text":"may","location":[2601,2604],"confidence":0.8},{"text":"may","location":[10775,10778],"confidence":0.8},{"text":"may","location":[13585,13588],"confidence":0.8},{"text":"may","location":[21787,21790],"confidence":0.8}],"count":3,"confidence":0.8,"usefulness":false,"Metadata":null},{"type":"DATE","subcategory":"DURATION","text":"12 months","sentiment":{"score":0.0,"label":null},"relevance":0.0,"mentions":[{"text":"12 months","location":[10619,10628],"confidence":0.8}],"count":0,"confidence":0.8,"usefulness":false,"Metadata":null},{"type":"DATE","subcategory":"SET","text":"semiannual","sentiment":{"score":0.0,"label":null},"relevance":0.0,"mentions":[{"text":"semiannual","location":[18302,18312],"confidence":0.8}],"count":0,"confidence":0.8,"usefulness":false,"Metadata":null},{"type":"DATE","subcategory":"DURATION","text":"48 hours","sentiment":{"score":0.0,"label":null},"relevance":0.0,"mentions":[{"text":"48 hours","location":[20079,20087],"confidence":0.8},{"text":"48 hours","location":[20887,20895],"confidence":0.8}],"count":1,"confidence":0.8,"usefulness":false,"Metadata":null},{"type":"DATE","subcategory":"DURATION","text":"less than a minute","sentiment":{"score":0.0,"label":null},"relevance":0.0,"mentions":[{"text":"less than a minute","location":[21274,21292],"confidence":0.8}],"count":0,"confidence":0.8,"usefulness":false,"Metadata":null},{"type":"DATE","subcategory":"DURATION","text":"6 months","sentiment":{"score":0.0,"label":null},"relevance":0.0,"mentions":[{"text":"6 months","location":[21482,21490],"confidence":0.8}],"count":0,"confidence":0.8,"usefulness":false,"Metadata":null},{"type":"DATE","subcategory":"DATE","text":"March 25, 2019","sentiment":{"score":0.0,"label":null},"relevance":0.0,"mentions":[{"text":"March 25, 2019","location":[22107,22121],"confidence":0.8}],"count":0,"confidence":0.8,"usefulness":false,"Metadata":null},{"type":"DATE","subcategory":"DATE","text":"March 24, 2021","sentiment":{"score":0.0,"label":null},"relevance":0.0,"mentions":[{"text":"March 24, 2021","location":[22325,22339],"confidence":0.8}],"count":0,"confidence":0.8,"usefulness":false,"Metadata":null},{"type":"DATE","subcategory":"DATE","text":"August 14, 2018","sentiment":{"score":0.0,"label":null},"relevance":0.0,"mentions":[{"text":"August 14, 2018","location":[23151,23166],"confidence":0.8}],"count":0,"confidence":0.8,"usefulness":false,"Metadata":null},{"type":"EVENT","subcategory":"","text":"Secret Chats","sentiment":{"score":0.0,"label":null},"relevance":0.0,"mentions":[{"text":"Secret Chats","location":[21001,21013],"confidence":0.5}],"count":0,"confidence":0.5,"usefulness":false,"Metadata":null},{"type":"LOCATION","subcategory":"GPE","text":"European Economic Area","sentiment":{"score":0.0,"label":null},"relevance":0.0,"mentions":[{"text":"European Economic Area","location":[1426,1448],"confidence":0.49}],"count":0,"confidence":0.49,"usefulness":false,"Metadata":null},{"type":"LOCATION","subcategory":"GPE","text":"EEA","sentiment":{"score":0.0,"label":null},"relevance":0.0,"mentions":[{"text":"EEA","location":[1450,1453],"confidence":0.5}],"count":0,"confidence":0.5,"usefulness":false,"Metadata":null},{"type":"LOCATION","subcategory":"","text":"data centers","sentiment":{"score":0.0,"label":null},"relevance":0.0,"mentions":[{"text":"data centers","location":[4074,4086],"confidence":0.81},{"text":"data centers","location":[8392,8404],"confidence":0.79},{"text":"data centers","location":[8456,8468],"confidence":0.78},{"text":"data centers","location":[8569,8581],"confidence":0.89},{"text":"data centers","location":[8701,8713],"confidence":0.83}],"count":4,"confidence":0.8,"usefulness":false,"Metadata":null},{"type":"LOCATION","subcategory":"GPE","text":"UK","sentiment":{"score":0.0,"label":null},"relevance":0.0,"mentions":[{"text":"UK","location":[8354,8356],"confidence":1.0}],"count":0,"confidence":1.0,"usefulness":false,"Metadata":null},{"type":"LOCATION","subcategory":"GPE","text":"Netherlands","sentiment":{"score":0.0,"label":null},"relevance":0.0,"mentions":[{"text":"Netherlands","location":[8412,8423],"confidence":1.0}],"count":0,"confidence":1.0,"usefulness":false,"Metadata":null},{"type":"LOCATION","subcategory":"GPE","text":"British Virgin Islands","sentiment":{"score":0.0,"label":null},"relevance":0.0,"mentions":[{"text":"British Virgin Islands","location":[17540,17562],"confidence":0.96}],"count":0,"confidence":0.96,"usefulness":false,"Metadata":null},{"type":"LOCATION","subcategory":"GPE","text":"Dubai","sentiment":{"score":0.0,"label":null},"relevance":0.0,"mentions":[{"text":"Dubai","location":[17615,17620],"confidence":1.0}],"count":0,"confidence":1.0,"usefulness":false,"Metadata":null},{"type":"ORGANIZATION","subcategory":"","text":"Telegram","sentiment":{"score":0.0,"label":null},"relevance":0.0,"mentions":[{"text":"Telegram","location":[0,8],"confidence":0.92},{"text":"Telegram","location":[109,117],"confidence":0.92},{"text":"Telegram","location":[386,394],"confidence":0.61},{"text":"Telegram","location":[474,482],"confidence":0.95},{"text":"Telegram","location":[651,659],"confidence":0.72},{"text":"Telegram","location":[1485,1493],"confidence":0.96},{"text":"Telegram","location":[1657,1665],"confidence":0.93},{"text":"Telegram","location":[2503,2511],"confidence":0.51},{"text":"Telegram","location":[2678,2686],"confidence":0.87},{"text":"Telegram","location":[2895,2903],"confidence":0.74},{"text":"Telegram","location":[3745,3753],"confidence":0.63},{"text":"Telegram","location":[5226,5234],"confidence":0.84},{"text":"Telegram","location":[5588,5596],"confidence":0.89},{"text":"Telegram","location":[5725,5733],"confidence":0.78},{"text":"Telegram","location":[5923,5931],"confidence":0.87},{"text":"Telegram","location":[6232,6240],"confidence":0.41},{"text":"Telegram","location":[6570,6578],"confidence":0.7},{"text":"Telegram","location":[6743,6751],"confidence":0.84},{"text":"Telegram","location":[6908,6916],"confidence":0.83},{"text":"Telegram","location":[7023,7031],"confidence":0.87},{"text":"Telegram","location":[7133,7141],"confidence":0.86},{"text":"Telegram","location":[7500,7508],"confidence":0.69},{"text":"Telegram","location":[8336,8344],"confidence":0.48},{"text":"Telegram","location":[8478,8486],"confidence":0.98},{"text":"Telegram","location":[8637,8645],"confidence":0.99},{"text":"Telegram","location":[8766,8774],"confidence":0.59},{"text":"Telegram","location":[9203,9211],"confidence":0.77},{"text":"Telegram","location":[9871,9879],"confidence":0.63},{"text":"Telegram","location":[10128,10136],"confidence":0.93},{"text":"Telegram","location":[10237,10245],"confidence":0.93},{"text":"Telegram","location":[10731,10739],"confidence":0.45},{"text":"Telegram","location":[11288,11296],"confidence":0.62},{"text":"Telegram","location":[11442,11450],"confidence":0.51},{"text":"Telegram","location":[11521,11529],"confidence":0.76},{"text":"Telegram","location":[12133,12141],"confidence":0.88},{"text":"Telegram","location":[12271,12279],"confidence":0.77},{"text":"Telegram","location":[12379,12387],"confidence":0.77},{"text":"Telegram","location":[14216,14224],"confidence":0.97},{"text":"Telegram","location":[14317,14325],"confidence":0.98},{"text":"Telegram","location":[14605,14613],"confidence":0.96},{"text":"Telegram","location":[14803,14811],"confidence":0.97},{"text":"Telegram","location":[14973,14981],"confidence":0.98},{"text":"Telegram","location":[15357,15365],"confidence":0.92},{"text":"Telegram","location":[16132,16140],"confidence":0.54},{"text":"Telegram","location":[16496,16504],"confidence":0.66},{"text":"Telegram","location":[17076,17084],"confidence":0.64},{"text":"Telegram","location":[17413,17421],"confidence":0.96},{"text":"Telegram","location":[18082,18090],"confidence":0.8},{"text":"Telegram","location":[19365,19373],"confidence":0.95},{"text":"Telegram","location":[19487,19495],"confidence":0.71},{"text":"Telegram","location":[19773,19781],"confidence":0.83},{"text":"Telegram","location":[19828,19836],"confidence":0.71},{"text":"Telegram","location":[21437,21445],"confidence":0.4},{"text":"Telegram","location":[21609,21617],"confidence":0.76},{"text":"Telegram","location":[22513,22521],"confidence":0.64},{"text":"Telegram","location":[22821,22829],"confidence":0.39},{"text":"Telegram Messenger Inc.","location":[83,106],"confidence":0.97},{"text":"Telegram UK Holdings Ltd","location":[1751,1775],"confidence":0.98},{"text":"Telegram Web","location":[8243,8255],"confidence":0.65},{"text":"Telegram Group Inc","location":[17505,17523],"confidence":0.99},{"text":"Telegram FZ-LLC","location":[17572,17587],"confidence":0.97}],"count":45,"confidence":0.744375,"usefulness":false,"Metadata":null},{"type":"ORGANIZATION","subcategory":"","text":"Telegram Messenger Inc.","sentiment":{"score":0.0,"label":null},"relevance":0.0,"mentions":[{"text":"Telegram Messenger Inc.","location":[83,106],"confidence":0.97}],"count":0,"confidence":0.97,"usefulness":false,"Metadata":null},{"type":"ORGANIZATION","subcategory":"","text":"EEA","sentiment":{"score":0.0,"label":null},"relevance":0.0,"mentions":[{"text":"EEA","location":[1372,1375],"confidence":0.83},{"text":"EEA","location":[1689,1692],"confidence":0.82},{"text":"EEA","location":[1724,1727],"confidence":0.46},{"text":"EEA","location":[8364,8367],"confidence":0.54},{"text":"EEA","location":[16970,16973],"confidence":0.96}],"count":2,"confidence":0.8225,"usefulness":false,"Metadata":null},{"type":"ORGANIZATION","subcategory":"","text":"Telegram UK Holdings Ltd","sentiment":{"score":0.0,"label":null},"relevance":0.0,"mentions":[{"text":"Telegram UK Holdings Ltd","location":[1751,1775],"confidence":0.98}],"count":0,"confidence":0.98,"usefulness":false,"Metadata":null},{"type":"ORGANIZATION","subcategory":"","text":"Telegram Web","sentiment":{"score":0.0,"label":null},"relevance":0.0,"mentions":[{"text":"Telegram Web","location":[8243,8255],"confidence":0.65}],"count":0,"confidence":0.65,"usefulness":false,"Metadata":null},{"type":"ORGANIZATION","subcategory":"","text":"Telegram Group Inc","sentiment":{"score":0.0,"label":null},"relevance":0.0,"mentions":[{"text":"Telegram Group Inc","location":[17505,17523],"confidence":0.99}],"count":0,"confidence":0.99,"usefulness":false,"Metadata":null},{"type":"ORGANIZATION","subcategory":"","text":"Telegram FZ-LLC","sentiment":{"score":0.0,"label":null},"relevance":0.0,"mentions":[{"text":"Telegram FZ-LLC","location":[17572,17587],"confidence":0.97}],"count":0,"confidence":0.97,"usefulness":false,"Metadata":null},{"type":"ORGANIZATION","subcategory":"","text":"European Commission","sentiment":{"score":0.0,"label":null},"relevance":0.0,"mentions":[{"text":"European Commission","location":[17844,17863],"confidence":0.99}],"count":0,"confidence":0.99,"usefulness":false,"Metadata":null},{"type":"ORGANIZATION","subcategory":"","text":"EU","sentiment":{"score":0.0,"label":null},"relevance":0.0,"mentions":[{"text":"EU","location":[23202,23204],"confidence":0.74}],"count":0,"confidence":0.74,"usefulness":false,"Metadata":null},{"type":"PERSON","subcategory":"","text":"Johnny Depp","sentiment":{"score":0.0,"label":null},"relevance":0.0,"mentions":[{"text":"Johnny Depp","location":[3210,3221],"confidence":0.99}],"count":0,"confidence":0.99,"usefulness":false,"Metadata":null},{"type":"PERSONTYPE","subcategory":"","text":"user","sentiment":{"score":0.0,"label":null},"relevance":0.0,"mentions":[{"text":"user","location":[425,429],"confidence":0.83},{"text":"automated user","location":[13080,13094],"confidence":0.47}],"count":0,"confidence":0.83,"usefulness":false,"Metadata":null},{"type":"PERSONTYPE","subcategory":"","text":"Representative","sentiment":{"score":0.0,"label":null},"relevance":0.0,"mentions":[{"text":"Representative","location":[1376,1390],"confidence":0.82}],"count":0,"confidence":0.82,"usefulness":false,"Metadata":null},{"type":"PERSONTYPE","subcategory":"","text":"representative","sentiment":{"score":0.0,"label":null},"relevance":0.0,"mentions":[{"text":"representative","location":[1847,1861],"confidence":0.78}],"count":0,"confidence":0.78,"usefulness":false,"Metadata":null},{"type":"PERSONTYPE","subcategory":"","text":"users","sentiment":{"score":0.0,"label":null},"relevance":0.0,"mentions":[{"text":"users","location":[2190,2195],"confidence":0.92},{"text":"users","location":[3061,3066],"confidence":0.94},{"text":"users","location":[7562,7567],"confidence":0.93},{"text":"users","location":[10277,10282],"confidence":0.94},{"text":"users","location":[12388,12393],"confidence":0.92},{"text":"users","location":[14579,14584],"confidence":0.93},{"text":"users","location":[14645,14650],"confidence":0.94},{"text":"users","location":[16845,16850],"confidence":0.8},{"text":"users","location":[17067,17072],"confidence":0.83},{"text":"users","location":[17166,17171],"confidence":0.94}],"count":8,"confidence":0.93125,"usefulness":false,"Metadata":null},{"type":"PERSONTYPE","subcategory":"","text":"contacts","sentiment":{"score":0.0,"label":null},"relevance":0.0,"mentions":[{"text":"contacts","location":[2726,2734],"confidence":0.72},{"text":"contacts","location":[6155,6163],"confidence":0.62},{"text":"contacts","location":[6210,6218],"confidence":0.67},{"text":"contacts","location":[6391,6399],"confidence":0.62},{"text":"contacts","location":[6675,6683],"confidence":0.67}],"count":4,"confidence":0.67,"usefulness":false,"Metadata":null},{"type":"PERSONTYPE","subcategory":"","text":"mother","sentiment":{"score":0.0,"label":null},"relevance":0.0,"mentions":[{"text":"mother","location":[3177,3183],"confidence":0.98}],"count":0,"confidence":0.98,"usefulness":false,"Metadata":null},{"type":"PERSONTYPE","subcategory":"","text":"Mom","sentiment":{"score":0.0,"label":null},"relevance":0.0,"mentions":[{"text":"Mom","location":[3243,3246],"confidence":0.89}],"count":0,"confidence":0.89,"usefulness":false,"Metadata":null},{"type":"PERSONTYPE","subcategory":"","text":"Boss","sentiment":{"score":0.0,"label":null},"relevance":0.0,"mentions":[{"text":"Boss","location":[3263,3267],"confidence":0.75}],"count":0,"confidence":0.75,"usefulness":false,"Metadata":null},{"type":"PERSONTYPE","subcategory":"","text":"underlings","sentiment":{"score":0.0,"label":null},"relevance":0.0,"mentions":[{"text":"underlings","location":[3276,3286],"confidence":0.8}],"count":0,"confidence":0.8,"usefulness":false,"Metadata":null},{"type":"PERSONTYPE","subcategory":"","text":"engineers","sentiment":{"score":0.0,"label":null},"relevance":0.0,"mentions":[{"text":"engineers","location":[4130,4139],"confidence":0.97},{"text":"engineers","location":[8775,8784],"confidence":0.86}],"count":1,"confidence":0.915,"usefulness":false,"Metadata":null},{"type":"PERSONTYPE","subcategory":"","text":"intruders","sentiment":{"score":0.0,"label":null},"relevance":0.0,"mentions":[{"text":"intruders","location":[4152,4161],"confidence":0.41},{"text":"intruders","location":[8797,8806],"confidence":0.47}],"count":1,"confidence":0.44,"usefulness":false,"Metadata":null},{"type":"PERSONTYPE","subcategory":"","text":"recipient","sentiment":{"score":0.0,"label":null},"relevance":0.0,"mentions":[{"text":"recipient","location":[4329,4338],"confidence":0.93},{"text":"recipient","location":[5119,5128],"confidence":0.9},{"text":"recipient","location":[5340,5349],"confidence":0.91},{"text":"recipient","location":[9084,9093],"confidence":0.91},{"text":"recipient","location":[9186,9195],"confidence":0.9},{"text":"recipient","location":[9284,9293],"confidence":0.9}],"count":5,"confidence":0.9125,"usefulness":false,"Metadata":null},{"type":"PERSONTYPE","subcategory":"","text":"server","sentiment":{"score":0.0,"label":null},"relevance":0.0,"mentions":[{"text":"server","location":[4996,5002],"confidence":0.84}],"count":0,"confidence":0.84,"usefulness":false,"Metadata":null},{"type":"PERSONTYPE","subcategory":"","text":"Contacts","sentiment":{"score":0.0,"label":null},"relevance":0.0,"mentions":[{"text":"Contacts","location":[5911,5919],"confidence":0.53}],"count":0,"confidence":0.53,"usefulness":false,"Metadata":null},{"type":"PERSONTYPE","subcategory":"","text":"friends","sentiment":{"score":0.0,"label":null},"relevance":0.0,"mentions":[{"text":"friends","location":[6606,6613],"confidence":0.76}],"count":0,"confidence":0.76,"usefulness":false,"Metadata":null},{"type":"PERSONTYPE","subcategory":"","text":"police","sentiment":{"score":0.0,"label":null},"relevance":0.0,"mentions":[{"text":"police","location":[10183,10189],"confidence":0.77}],"count":0,"confidence":0.77,"usefulness":false,"Metadata":null},{"type":"PERSONTYPE","subcategory":"","text":"spammers","sentiment":{"score":0.0,"label":null},"relevance":0.0,"mentions":[{"text":"spammers","location":[10321,10329],"confidence":0.98}],"count":0,"confidence":0.98,"usefulness":false,"Metadata":null},{"type":"PERSONTYPE","subcategory":"","text":"moderators","sentiment":{"score":0.0,"label":null},"relevance":0.0,"mentions":[{"text":"moderators","location":[10764,10774],"confidence":0.94},{"text":"moderators","location":[10901,10911],"confidence":0.93}],"count":0,"confidence":0.94,"usefulness":false,"Metadata":null},{"type":"PERSONTYPE","subcategory":"","text":"recipients","sentiment":{"score":0.0,"label":null},"relevance":0.0,"mentions":[{"text":"recipients","location":[10830,10840],"confidence":0.92}],"count":0,"confidence":0.92,"usefulness":false,"Metadata":null},{"type":"PERSONTYPE","subcategory":"","text":"strangers","sentiment":{"score":0.0,"label":null},"relevance":0.0,"mentions":[{"text":"strangers","location":[10957,10966],"confidence":0.97}],"count":0,"confidence":0.97,"usefulness":false,"Metadata":null},{"type":"PERSONTYPE","subcategory":"","text":"developers","sentiment":{"score":0.0,"label":null},"relevance":0.0,"mentions":[{"text":"developers","location":[12315,12325],"confidence":0.85},{"text":"developers","location":[12698,12708],"confidence":0.62},{"text":"developers","location":[13063,13073],"confidence":0.92},{"text":"developers","location":[14286,14296],"confidence":0.39},{"text":"developers","location":[16687,16697],"confidence":0.38},{"text":"bot developers","location":[12622,12636],"confidence":0.51},{"text":"bot developers","location":[14847,14861],"confidence":0.73}],"count":2,"confidence":0.62,"usefulness":false,"Metadata":null},{"type":"PERSONTYPE","subcategory":"","text":"bot developers","sentiment":{"score":0.0,"label":null},"relevance":0.0,"mentions":[{"text":"bot developers","location":[12622,12636],"confidence":0.51},{"text":"bot developers","location":[14847,14861],"confidence":0.73}],"count":1,"confidence":0.62,"usefulness":false,"Metadata":null},{"type":"PERSONTYPE","subcategory":"","text":"bot","sentiment":{"score":0.0,"label":null},"relevance":0.0,"mentions":[{"text":"bot","location":[12694,12697],"confidence":0.79},{"text":"bot","location":[14143,14146],"confidence":0.61},{"text":"bot","location":[14282,14285],"confidence":0.65},{"text":"bot","location":[16683,16686],"confidence":0.52},{"text":"bot developers","location":[12622,12636],"confidence":0.51},{"text":"bot developers","location":[14847,14861],"confidence":0.73},{"text":"merchant bot developer","location":[15823,15845],"confidence":0.57}],"count":3,"confidence":0.70000005,"usefulness":false,"Metadata":null},{"type":"PERSONTYPE","subcategory":"","text":"Data","sentiment":{"score":0.0,"label":null},"relevance":0.0,"mentions":[{"text":"Data","location":[13011,13015],"confidence":0.54}],"count":0,"confidence":0.54,"usefulness":false,"Metadata":null},{"type":"PERSONTYPE","subcategory":"","text":"automated user","sentiment":{"score":0.0,"label":null},"relevance":0.0,"mentions":[{"text":"automated user","location":[13080,13094],"confidence":0.47}],"count":0,"confidence":0.47,"usefulness":false,"Metadata":null},{"type":"PERSONTYPE","subcategory":"","text":"member","sentiment":{"score":0.0,"label":null},"relevance":0.0,"mentions":[{"text":"member","location":[13547,13553],"confidence":0.83},{"text":"member","location":[13604,13610],"confidence":0.94}],"count":0,"confidence":0.83,"usefulness":false,"Metadata":null},{"type":"PERSONTYPE","subcategory":"","text":"merchants","sentiment":{"score":0.0,"label":null},"relevance":0.0,"mentions":[{"text":"merchants","location":[14820,14829],"confidence":0.81}],"count":0,"confidence":0.81,"usefulness":false,"Metadata":null},{"type":"PERSONTYPE","subcategory":"","text":"merchant bot developer","sentiment":{"score":0.0,"label":null},"relevance":0.0,"mentions":[{"text":"merchant bot developer","location":[15823,15845],"confidence":0.57}],"count":0,"confidence":0.57,"usefulness":false,"Metadata":null},{"type":"PERSONTYPE","subcategory":"","text":"providers","sentiment":{"score":0.0,"label":null},"relevance":0.0,"mentions":[{"text":"providers","location":[16353,16362],"confidence":0.65}],"count":0,"confidence":0.65,"usefulness":false,"Metadata":null},{"type":"PERSONTYPE","subcategory":"","text":"Users","sentiment":{"score":0.0,"label":null},"relevance":0.0,"mentions":[{"text":"Users","location":[16830,16835],"confidence":0.84}],"count":0,"confidence":0.84,"usefulness":false,"Metadata":null},{"type":"PERSONTYPE","subcategory":"","text":"terror suspect","sentiment":{"score":0.0,"label":null},"relevance":0.0,"mentions":[{"text":"terror suspect","location":[18137,18151],"confidence":0.76}],"count":0,"confidence":0.76,"usefulness":false,"Metadata":null},{"type":"PERSONTYPE","subcategory":"","text":"authorities","sentiment":{"score":0.0,"label":null},"relevance":0.0,"mentions":[{"text":"authorities","location":[18218,18229],"confidence":0.69}],"count":0,"confidence":0.69,"usefulness":false,"Metadata":null},{"type":"PERSONTYPE","subcategory":"","text":"data controller","sentiment":{"score":0.0,"label":null},"relevance":0.0,"mentions":[{"text":"data controller","location":[18693,18708],"confidence":0.88}],"count":0,"confidence":0.88,"usefulness":false,"Metadata":null},{"type":"PERSONTYPE","subcategory":"","text":"participants","sentiment":{"score":0.0,"label":null},"relevance":0.0,"mentions":[{"text":"participants","location":[20050,20062],"confidence":0.95},{"text":"participants","location":[20687,20699],"confidence":0.97},{"text":"participants","location":[20773,20785],"confidence":0.98},{"text":"participants","location":[22227,22239],"confidence":0.93}],"count":0,"confidence":0.95,"usefulness":false,"Metadata":null},{"type":"PERSONTYPE","subcategory":"","text":"partner","sentiment":{"score":0.0,"label":null},"relevance":0.0,"mentions":[{"text":"partner","location":[20238,20245],"confidence":0.96},{"text":"partner","location":[20281,20288],"confidence":0.99}],"count":0,"confidence":0.96,"usefulness":false,"Metadata":null},{"type":"PERSONTYPE","subcategory":"","text":"admins","sentiment":{"score":0.0,"label":null},"relevance":0.0,"mentions":[{"text":"admins","location":[20939,20945],"confidence":0.73}],"count":0,"confidence":0.73,"usefulness":false,"Metadata":null},{"type":"PRODUCT","subcategory":"","text":"Telegram Passport","sentiment":{"score":0.0,"label":null},"relevance":0.0,"mentions":[{"text":"Telegram Passport","location":[3486,3503],"confidence":0.72},{"text":"Telegram Passport","location":[9006,9023],"confidence":0.61},{"text":"Telegram Passport","location":[9323,9340],"confidence":0.75}],"count":2,"confidence":0.665,"usefulness":false,"Metadata":null},{"type":"PRODUCT","subcategory":"","text":"devices","sentiment":{"score":0.0,"label":null},"relevance":0.0,"mentions":[{"text":"devices","location":[11356,11363],"confidence":0.66}],"count":0,"confidence":0.66,"usefulness":false,"Metadata":null},{"type":"PRODUCT","subcategory":"","text":"Bots","sentiment":{"score":0.0,"label":null},"relevance":0.0,"mentions":[{"text":"Bots","location":[12648,12652],"confidence":0.87},{"text":"Bots","location":[13213,13217],"confidence":0.41},{"text":"Bots","location":[13290,13294],"confidence":0.58}],"count":0,"confidence":0.87,"usefulness":false,"Metadata":null},{"type":"PRODUCT","subcategory":"","text":"bot","sentiment":{"score":0.0,"label":null},"relevance":0.0,"mentions":[{"text":"bot","location":[12797,12800],"confidence":0.79},{"text":"bot","location":[12826,12829],"confidence":0.47},{"text":"bot","location":[12871,12874],"confidence":0.55},{"text":"bot","location":[12923,12926],"confidence":0.57},{"text":"bot","location":[13421,13424],"confidence":0.53},{"text":"bot","location":[13800,13803],"confidence":0.78},{"text":"inline bot","location":[13894,13904],"confidence":0.66}],"count":1,"confidence":0.78499997,"usefulness":false,"Metadata":null},{"type":"PRODUCT","subcategory":"","text":"inline bot","sentiment":{"score":0.0,"label":null},"relevance":0.0,"mentions":[{"text":"inline bot","location":[13894,13904],"confidence":0.66}],"count":0,"confidence":0.66,"usefulness":false,"Metadata":null},{"type":"PRODUCT","subcategory":"","text":"bots","sentiment":{"score":0.0,"label":null},"relevance":0.0,"mentions":[{"text":"bots","location":[14247,14251],"confidence":0.52}],"count":0,"confidence":0.52,"usefulness":false,"Metadata":null},{"type":"PRODUCT","subcategory":"","text":"Telegram","sentiment":{"score":0.0,"label":null},"relevance":0.0,"mentions":[{"text":"Telegram","location":[16821,16829],"confidence":0.45},{"text":"Telegram","location":[22705,22713],"confidence":0.48},{"text":"Telegram Passport","location":[3486,3503],"confidence":0.72},{"text":"Telegram Passport","location":[9006,9023],"confidence":0.61},{"text":"Telegram Passport","location":[9323,9340],"confidence":0.75}],"count":1,"confidence":0.46499997,"usefulness":false,"Metadata":null},{"type":"PRODUCT","subcategory":"","text":"timer","sentiment":{"score":0.0,"label":null},"relevance":0.0,"mentions":[{"text":"timer","location":[21331,21336],"confidence":0.5}],"count":0,"confidence":0.5,"usefulness":false,"Metadata":null},{"type":"QUANTITY","subcategory":"NUMBER","text":"1","sentiment":{"score":0.0,"label":null},"relevance":0.0,"mentions":[{"text":"1","location":[27,28],"confidence":0.8},{"text":"1","location":[2136,2137],"confidence":0.8},{"text":"1","location":[3727,3728],"confidence":0.8},{"text":"1","location":[5696,5697],"confidence":0.8},{"text":"1","location":[17482,17483],"confidence":0.8},{"text":"1","location":[18598,18599],"confidence":0.8}],"count":3,"confidence":0.8,"usefulness":false,"Metadata":null},{"type":"QUANTITY","subcategory":"NUMBER","text":"1.1","sentiment":{"score":0.0,"label":null},"relevance":0.0,"mentions":[{"text":"1.1","location":[448,451],"confidence":0.8}],"count":0,"confidence":0.8,"usefulness":false,"Metadata":null},{"type":"QUANTITY","subcategory":"NUMBER","text":"two","sentiment":{"score":0.0,"label":null},"relevance":0.0,"mentions":[{"text":"two","location":[487,490],"confidence":0.8},{"text":"two","location":[13947,13950],"confidence":0.8}],"count":1,"confidence":0.8,"usefulness":false,"Metadata":null},{"type":"QUANTITY","subcategory":"NUMBER","text":"1.2","sentiment":{"score":0.0,"label":null},"relevance":0.0,"mentions":[{"text":"1.2","location":[729,732],"confidence":0.8}],"count":0,"confidence":0.8,"usefulness":false,"Metadata":null},{"type":"QUANTITY","subcategory":"NUMBER","text":"1.3","sentiment":{"score":0.0,"label":null},"relevance":0.0,"mentions":[{"text":"1.3","location":[1001,1004],"confidence":0.8}],"count":0,"confidence":0.8,"usefulness":false,"Metadata":null},{"type":"QUANTITY","subcategory":"NUMBER","text":"1.4","sentiment":{"score":0.0,"label":null},"relevance":0.0,"mentions":[{"text":"1.4","location":[1367,1370],"confidence":0.8}],"count":0,"confidence":0.8,"usefulness":false,"Metadata":null},{"type":"QUANTITY","subcategory":"NUMBER","text":"one","sentiment":{"score":0.0,"label":null},"relevance":0.0,"mentions":[{"text":"one","location":[1713,1716],"confidence":0.8},{"text":"one","location":[2887,2890],"confidence":0.8},{"text":"one","location":[5219,5222],"confidence":0.8},{"text":"one","location":[6198,6201],"confidence":0.8},{"text":"one","location":[12746,12749],"confidence":0.8},{"text":"one","location":[19308,19311],"confidence":0.8},{"text":"one","location":[20395,20398],"confidence":0.8},{"text":"one","location":[20402,20405],"confidence":0.8},{"text":"one","location":[22268,22271],"confidence":0.8},{"text":"one","location":[22275,22278],"confidence":0.8}],"count":8,"confidence":0.8,"usefulness":false,"Metadata":null},{"type":"QUANTITY","subcategory":"NUMBER","text":"71","sentiment":{"score":0.0,"label":null},"relevance":0.0,"mentions":[{"text":"71","location":[1777,1779],"confidence":0.8}],"count":0,"confidence":0.8,"usefulness":false,"Metadata":null},{"type":"QUANTITY","subcategory":"NUMBER","text":"75","sentiment":{"score":0.0,"label":null},"relevance":0.0,"mentions":[{"text":"75","location":[1780,1782],"confidence":0.8}],"count":0,"confidence":0.8,"usefulness":false,"Metadata":null},{"type":"QUANTITY","subcategory":"NUMBER","text":"2","sentiment":{"score":0.0,"label":null},"relevance":0.0,"mentions":[{"text":"2","location":[1956,1957],"confidence":0.8},{"text":"2","location":[2202,2203],"confidence":0.8},{"text":"2","location":[3420,3421],"confidence":0.8},{"text":"2","location":[4199,4200],"confidence":0.8},{"text":"2","location":[8927,8928],"confidence":0.8},{"text":"2","location":[17569,17570],"confidence":0.8},{"text":"2","location":[18711,18712],"confidence":0.8},{"text":"2","location":[21082,21083],"confidence":0.8}],"count":4,"confidence":0.8,"usefulness":false,"Metadata":null},{"type":"QUANTITY","subcategory":"NUMBER","text":"3","sentiment":{"score":0.0,"label":null},"relevance":0.0,"mentions":[{"text":"3","location":[2446,2447],"confidence":0.8},{"text":"3","location":[3723,3724],"confidence":0.8},{"text":"3","location":[3725,3726],"confidence":0.8},{"text":"3","location":[4195,4196],"confidence":0.8},{"text":"3","location":[4197,4198],"confidence":0.8},{"text":"3","location":[4824,4825],"confidence":0.8},{"text":"3","location":[4826,4827],"confidence":0.8},{"text":"3","location":[4828,4829],"confidence":0.8},{"text":"3","location":[5532,5533],"confidence":0.8},{"text":"3","location":[5534,5535],"confidence":0.8},{"text":"3","location":[5692,5693],"confidence":0.8},{"text":"3","location":[5694,5695],"confidence":0.8},{"text":"3","location":[8923,8924],"confidence":0.8},{"text":"3","location":[8925,8926],"confidence":0.8},{"text":"3","location":[18774,18775],"confidence":0.8},{"text":"3","location":[22405,22406],"confidence":0.8},{"text":"3","location":[22407,22408],"confidence":0.8},{"text":"3","location":[22422,22423],"confidence":0.8},{"text":"3","location":[22424,22425],"confidence":0.8}],"count":14,"confidence":0.8,"usefulness":false,"Metadata":null},{"type":"QUANTITY","subcategory":"NUMBER","text":"3.1","sentiment":{"score":0.0,"label":null},"relevance":0.0,"mentions":[{"text":"3.1","location":[2476,2479],"confidence":0.8},{"text":"3.1","location":[13147,13150],"confidence":0.8}],"count":1,"confidence":0.8,"usefulness":false,"Metadata":null},{"type":"QUANTITY","subcategory":"AGE","text":"age","sentiment":{"score":0.0,"label":null},"relevance":0.0,"mentions":[{"text":"age","location":[2969,2972],"confidence":0.8}],"count":0,"confidence":0.8,"usefulness":false,"Metadata":null},{"type":"QUANTITY","subcategory":"NUMBER","text":"3.2","sentiment":{"score":0.0,"label":null},"relevance":0.0,"mentions":[{"text":"3.2","location":[3376,3379],"confidence":0.8}],"count":0,"confidence":0.8,"usefulness":false,"Metadata":null},{"type":"QUANTITY","subcategory":"NUMBER","text":"3.3","sentiment":{"score":0.0,"label":null},"relevance":0.0,"mentions":[{"text":"3.3","location":[3703,3706],"confidence":0.8}],"count":0,"confidence":0.8,"usefulness":false,"Metadata":null},{"type":"QUANTITY","subcategory":"ORDINAL","text":"third","sentiment":{"score":0.0,"label":null},"relevance":0.0,"mentions":[{"text":"third","location":[3951,3956],"confidence":0.8},{"text":"third","location":[8435,8440],"confidence":0.8},{"text":"third","location":[10061,10066],"confidence":0.8},{"text":"third","location":[12303,12308],"confidence":0.8},{"text":"third","location":[12610,12615],"confidence":0.8},{"text":"third","location":[14270,14275],"confidence":0.8}],"count":5,"confidence":0.8,"usefulness":false,"Metadata":null},{"type":"QUANTITY","subcategory":"NUMBER","text":"4","sentiment":{"score":0.0,"label":null},"relevance":0.0,"mentions":[{"text":"4","location":[5536,5537],"confidence":0.8},{"text":"4","location":[8258,8259],"confidence":0.8},{"text":"4","location":[18840,18841],"confidence":0.8}],"count":1,"confidence":0.8,"usefulness":false,"Metadata":null},{"type":"QUANTITY","subcategory":"NUMBER","text":"3.4","sentiment":{"score":0.0,"label":null},"relevance":0.0,"mentions":[{"text":"3.4","location":[5889,5892],"confidence":0.8},{"text":"3.4","location":[22414,22417],"confidence":0.8}],"count":1,"confidence":0.8,"usefulness":false,"Metadata":null},{"type":"QUANTITY","subcategory":"ORDINAL","text":"first","sentiment":{"score":0.0,"label":null},"relevance":0.0,"mentions":[{"text":"first","location":[6323,6328],"confidence":0.8},{"text":"first","location":[13872,13877],"confidence":0.8}],"count":1,"confidence":0.8,"usefulness":false,"Metadata":null},{"type":"QUANTITY","subcategory":"NUMBER","text":"3.5","sentiment":{"score":0.0,"label":null},"relevance":0.0,"mentions":[{"text":"3.5","location":[7256,7259],"confidence":0.8},{"text":"3.5","location":[22353,22356],"confidence":0.8}],"count":1,"confidence":0.8,"usefulness":false,"Metadata":null},{"type":"QUANTITY","subcategory":"NUMBER","text":"3.6","sentiment":{"score":0.0,"label":null},"relevance":0.0,"mentions":[{"text":"3.6","location":[7688,7691],"confidence":0.8},{"text":"3.6","location":[22431,22434],"confidence":0.8}],"count":1,"confidence":0.8,"usefulness":false,"Metadata":null},{"type":"QUANTITY","subcategory":"NUMBER","text":"4.1","sentiment":{"score":0.0,"label":null},"relevance":0.0,"mentions":[{"text":"4.1","location":[8294,8297],"confidence":0.8}],"count":0,"confidence":0.8,"usefulness":false,"Metadata":null},{"type":"QUANTITY","subcategory":"NUMBER","text":"4.2","sentiment":{"score":0.0,"label":null},"relevance":0.0,"mentions":[{"text":"4.2","location":[8827,8830],"confidence":0.8}],"count":0,"confidence":0.8,"usefulness":false,"Metadata":null},{"type":"QUANTITY","subcategory":"NUMBER","text":"4.3","sentiment":{"score":0.0,"label":null},"relevance":0.0,"mentions":[{"text":"4.3","location":[9581,9584],"confidence":0.8}],"count":0,"confidence":0.8,"usefulness":false,"Metadata":null},{"type":"QUANTITY","subcategory":"NUMBER","text":"5","sentiment":{"score":0.0,"label":null},"relevance":0.0,"mentions":[{"text":"5","location":[9816,9817],"confidence":0.8},{"text":"5","location":[18915,18916],"confidence":0.8},{"text":"5","location":[22409,22410],"confidence":0.8}],"count":2,"confidence":0.8,"usefulness":false,"Metadata":null},{"type":"QUANTITY","subcategory":"NUMBER","text":"5.1","sentiment":{"score":0.0,"label":null},"relevance":0.0,"mentions":[{"text":"5.1","location":[9850,9853],"confidence":0.8}],"count":0,"confidence":0.8,"usefulness":false,"Metadata":null},{"type":"QUANTITY","subcategory":"NUMBER","text":"5.2","sentiment":{"score":0.0,"label":null},"relevance":0.0,"mentions":[{"text":"5.2","location":[10100,10103],"confidence":0.8}],"count":0,"confidence":0.8,"usefulness":false,"Metadata":null},{"type":"QUANTITY","subcategory":"NUMBER","text":"400 million","sentiment":{"score":0.0,"label":null},"relevance":0.0,"mentions":[{"text":"400 million","location":[10265,10276],"confidence":0.8}],"count":0,"confidence":0.8,"usefulness":false,"Metadata":null},{"type":"QUANTITY","subcategory":"NUMBER","text":"5.3","sentiment":{"score":0.0,"label":null},"relevance":0.0,"mentions":[{"text":"5.3","location":[10639,10642],"confidence":0.8}],"count":0,"confidence":0.8,"usefulness":false,"Metadata":null},{"type":"QUANTITY","subcategory":"NUMBER","text":"5.4","sentiment":{"score":0.0,"label":null},"relevance":0.0,"mentions":[{"text":"5.4","location":[11200,11203],"confidence":0.8}],"count":0,"confidence":0.8,"usefulness":false,"Metadata":null},{"type":"QUANTITY","subcategory":"NUMBER","text":"5.5","sentiment":{"score":0.0,"label":null},"relevance":0.0,"mentions":[{"text":"5.5","location":[11319,11322],"confidence":0.8},{"text":"5.5","location":[11366,11369],"confidence":0.8},{"text":"5.5","location":[20343,20346],"confidence":0.8},{"text":"5.5","location":[22205,22208],"confidence":0.8}],"count":2,"confidence":0.8,"usefulness":false,"Metadata":null},{"type":"QUANTITY","subcategory":"NUMBER","text":"5.6","sentiment":{"score":0.0,"label":null},"relevance":0.0,"mentions":[{"text":"5.6","location":[12025,12028],"confidence":0.8}],"count":0,"confidence":0.8,"usefulness":false,"Metadata":null},{"type":"QUANTITY","subcategory":"NUMBER","text":"6","sentiment":{"score":0.0,"label":null},"relevance":0.0,"mentions":[{"text":"6","location":[12236,12237],"confidence":0.8},{"text":"6","location":[22426,22427],"confidence":0.8}],"count":1,"confidence":0.8,"usefulness":false,"Metadata":null},{"type":"QUANTITY","subcategory":"NUMBER","text":"6.1","sentiment":{"score":0.0,"label":null},"relevance":0.0,"mentions":[{"text":"6.1","location":[12253,12256],"confidence":0.8}],"count":0,"confidence":0.8,"usefulness":false,"Metadata":null},{"type":"QUANTITY","subcategory":"NUMBER","text":"6.2","sentiment":{"score":0.0,"label":null},"relevance":0.0,"mentions":[{"text":"6.2","location":[12639,12642],"confidence":0.8}],"count":0,"confidence":0.8,"usefulness":false,"Metadata":null},{"type":"QUANTITY","subcategory":"NUMBER","text":"7","sentiment":{"score":0.0,"label":null},"relevance":0.0,"mentions":[{"text":"7","location":[12988,12989],"confidence":0.8},{"text":"7","location":[14472,14473],"confidence":0.8}],"count":1,"confidence":0.8,"usefulness":false,"Metadata":null},{"type":"QUANTITY","subcategory":"NUMBER","text":"6.3","sentiment":{"score":0.0,"label":null},"relevance":0.0,"mentions":[{"text":"6.3","location":[13001,13004],"confidence":0.8}],"count":0,"confidence":0.8,"usefulness":false,"Metadata":null},{"type":"QUANTITY","subcategory":"NUMBER","text":"6.4","sentiment":{"score":0.0,"label":null},"relevance":0.0,"mentions":[{"text":"6.4","location":[14184,14187],"confidence":0.8}],"count":0,"confidence":0.8,"usefulness":false,"Metadata":null},{"type":"QUANTITY","subcategory":"ORDINAL","text":"Third","sentiment":{"score":0.0,"label":null},"relevance":0.0,"mentions":[{"text":"Third","location":[14475,14480],"confidence":0.8}],"count":0,"confidence":0.8,"usefulness":false,"Metadata":null},{"type":"QUANTITY","subcategory":"NUMBER","text":"7.1","sentiment":{"score":0.0,"label":null},"relevance":0.0,"mentions":[{"text":"7.1","location":[14505,14508],"confidence":0.8}],"count":0,"confidence":0.8,"usefulness":false,"Metadata":null},{"type":"QUANTITY","subcategory":"NUMBER","text":"4.0","sentiment":{"score":0.0,"label":null},"relevance":0.0,"mentions":[{"text":"4.0","location":[14600,14603],"confidence":0.8}],"count":0,"confidence":0.8,"usefulness":false,"Metadata":null},{"type":"QUANTITY","subcategory":"NUMBER","text":"7.2","sentiment":{"score":0.0,"label":null},"relevance":0.0,"mentions":[{"text":"7.2","location":[15072,15075],"confidence":0.8}],"count":0,"confidence":0.8,"usefulness":false,"Metadata":null},{"type":"QUANTITY","subcategory":"NUMBER","text":"7.3","sentiment":{"score":0.0,"label":null},"relevance":0.0,"mentions":[{"text":"7.3","location":[15696,15699],"confidence":0.8}],"count":0,"confidence":0.8,"usefulness":false,"Metadata":null},{"type":"QUANTITY","subcategory":"NUMBER","text":"7.4","sentiment":{"score":0.0,"label":null},"relevance":0.0,"mentions":[{"text":"7.4","location":[16004,16007],"confidence":0.8}],"count":0,"confidence":0.8,"usefulness":false,"Metadata":null},{"type":"QUANTITY","subcategory":"NUMBER","text":"7.5","sentiment":{"score":0.0,"label":null},"relevance":0.0,"mentions":[{"text":"7.5","location":[16450,16453],"confidence":0.8}],"count":0,"confidence":0.8,"usefulness":false,"Metadata":null},{"type":"QUANTITY","subcategory":"NUMBER","text":"8","sentiment":{"score":0.0,"label":null},"relevance":0.0,"mentions":[{"text":"8","location":[16764,16765],"confidence":0.8}],"count":0,"confidence":0.8,"usefulness":false,"Metadata":null},{"type":"QUANTITY","subcategory":"NUMBER","text":"8.1","sentiment":{"score":0.0,"label":null},"relevance":0.0,"mentions":[{"text":"8.1","location":[16810,16813],"confidence":0.8}],"count":0,"confidence":0.8,"usefulness":false,"Metadata":null},{"type":"QUANTITY","subcategory":"NUMBER","text":"8.2","sentiment":{"score":0.0,"label":null},"relevance":0.0,"mentions":[{"text":"8.2","location":[17408,17411],"confidence":0.8}],"count":0,"confidence":0.8,"usefulness":false,"Metadata":null},{"type":"QUANTITY","subcategory":"NUMBER","text":"12","sentiment":{"score":0.0,"label":null},"relevance":0.0,"mentions":[{"text":"12","location":[18032,18034],"confidence":0.8},{"text":"12","location":[19150,19152],"confidence":0.8},{"text":"12","location":[22524,22526],"confidence":0.8}],"count":1,"confidence":0.8,"usefulness":false,"Metadata":null},{"type":"QUANTITY","subcategory":"NUMBER","text":"8.3","sentiment":{"score":0.0,"label":null},"relevance":0.0,"mentions":[{"text":"8.3","location":[18043,18046],"confidence":0.8}],"count":0,"confidence":0.8,"usefulness":false,"Metadata":null},{"type":"QUANTITY","subcategory":"NUMBER","text":"9","sentiment":{"score":0.0,"label":null},"relevance":0.0,"mentions":[{"text":"9","location":[18375,18376],"confidence":0.8}],"count":0,"confidence":0.8,"usefulness":false,"Metadata":null},{"type":"QUANTITY","subcategory":"NUMBER","text":"9.1","sentiment":{"score":0.0,"label":null},"relevance":0.0,"mentions":[{"text":"9.1","location":[18437,18440],"confidence":0.8}],"count":0,"confidence":0.8,"usefulness":false,"Metadata":null},{"type":"QUANTITY","subcategory":"NUMBER","text":"10","sentiment":{"score":0.0,"label":null},"relevance":0.0,"mentions":[{"text":"10","location":[18734,18736],"confidence":0.8},{"text":"10","location":[19545,19547],"confidence":0.8}],"count":0,"confidence":0.8,"usefulness":false,"Metadata":null},{"type":"QUANTITY","subcategory":"NUMBER","text":"9.2","sentiment":{"score":0.0,"label":null},"relevance":0.0,"mentions":[{"text":"9.2","location":[19027,19030],"confidence":0.8}],"count":0,"confidence":0.8,"usefulness":false,"Metadata":null},{"type":"QUANTITY","subcategory":"NUMBER","text":"9.3","sentiment":{"score":0.0,"label":null},"relevance":0.0,"mentions":[{"text":"9.3","location":[19161,19164],"confidence":0.8}],"count":0,"confidence":0.8,"usefulness":false,"Metadata":null},{"type":"QUANTITY","subcategory":"NUMBER","text":"10.1","sentiment":{"score":0.0,"label":null},"relevance":0.0,"mentions":[{"text":"10.1","location":[19564,19568],"confidence":0.8}],"count":0,"confidence":0.8,"usefulness":false,"Metadata":null},{"type":"QUANTITY","subcategory":"NUMBER","text":"10.2","sentiment":{"score":0.0,"label":null},"relevance":0.0,"mentions":[{"text":"10.2","location":[19868,19872],"confidence":0.8},{"text":"10.2","location":[22139,22143],"confidence":0.8}],"count":0,"confidence":0.8,"usefulness":false,"Metadata":null},{"type":"QUANTITY","subcategory":"NUMBER","text":"10.3","sentiment":{"score":0.0,"label":null},"relevance":0.0,"mentions":[{"text":"10.3","location":[20954,20958],"confidence":0.8}],"count":0,"confidence":0.8,"usefulness":false,"Metadata":null},{"type":"QUANTITY","subcategory":"NUMBER","text":"10.4","sentiment":{"score":0.0,"label":null},"relevance":0.0,"mentions":[{"text":"10.4","location":[21373,21377],"confidence":0.8}],"count":0,"confidence":0.8,"usefulness":false,"Metadata":null},{"type":"QUANTITY","subcategory":"NUMBER","text":"11","sentiment":{"score":0.0,"label":null},"relevance":0.0,"mentions":[{"text":"11","location":[21730,21732],"confidence":0.8}],"count":0,"confidence":0.8,"usefulness":false,"Metadata":null},{"type":"SKILL","subcategory":"","text":"messaging services","sentiment":{"score":0.0,"label":null},"relevance":0.0,"mentions":[{"text":"messaging services","location":[277,295],"confidence":0.72}],"count":0,"confidence":0.72,"usefulness":false,"Metadata":null},{"type":"SKILL","subcategory":"","text":"processing","sentiment":{"score":0.0,"label":null},"relevance":0.0,"mentions":[{"text":"processing","location":[546,556],"confidence":0.72},{"text":"processing","location":[1921,1931],"confidence":0.75},{"text":"processing","location":[18805,18815],"confidence":0.69},{"text":"processing","location":[18992,19002],"confidence":0.54}],"count":2,"confidence":0.70500004,"usefulness":false,"Metadata":null},{"type":"SKILL","subcategory":"","text":"data","sentiment":{"score":0.0,"label":null},"relevance":0.0,"mentions":[{"text":"data","location":[565,569],"confidence":0.48},{"text":"data","location":[596,600],"confidence":0.95},{"text":"data","location":[641,645],"confidence":0.54},{"text":"data","location":[1148,1152],"confidence":0.75},{"text":"data","location":[1209,1213],"confidence":0.59},{"text":"data","location":[1255,1259],"confidence":0.49},{"text":"data","location":[3887,3891],"confidence":0.93},{"text":"data","location":[5382,5386],"confidence":0.85},{"text":"data","location":[5489,5493],"confidence":0.78},{"text":"data","location":[6375,6379],"confidence":0.84},{"text":"data","location":[7523,7527],"confidence":0.72},{"text":"data","location":[8374,8378],"confidence":0.67},{"text":"data","location":[8456,8460],"confidence":0.69},{"text":"data","location":[8686,8690],"confidence":0.53},{"text":"data","location":[8983,8987],"confidence":0.84},{"text":"data","location":[9921,9925],"confidence":0.72},{"text":"data","location":[11419,11423],"confidence":0.58},{"text":"data","location":[12686,12690],"confidence":0.94},{"text":"data","location":[13249,13253],"confidence":0.95},{"text":"data","location":[14432,14436],"confidence":0.96},{"text":"data","location":[15047,15051],"confidence":0.76},{"text":"data","location":[19208,19212],"confidence":0.51},{"text":"data","location":[19751,19755],"confidence":0.51},{"text":"data","location":[23205,23209],"confidence":0.52},{"text":"data protection","location":[1532,1547],"confidence":0.59},{"text":"data protection","location":[18474,18489],"confidence":0.84},{"text":"user data","location":[4183,4192],"confidence":0.73},{"text":"encrypted data","location":[9248,9262],"confidence":0.47}],"count":17,"confidence":0.59406245,"usefulness":false,"Metadata":null},{"type":"SKILL","subcategory":"","text":"messaging","sentiment":{"score":0.0,"label":null},"relevance":0.0,"mentions":[{"text":"messaging","location":[707,716],"confidence":0.66},{"text":"messaging services","location":[277,295],"confidence":0.72}],"count":0,"confidence":0.66,"usefulness":false,"Metadata":null},{"type":"SKILL","subcategory":"","text":"data protection","sentiment":{"score":0.0,"label":null},"relevance":0.0,"mentions":[{"text":"data protection","location":[1532,1547],"confidence":0.59},{"text":"data protection","location":[18474,18489],"confidence":0.84}],"count":1,"confidence":0.715,"usefulness":false,"Metadata":null},{"type":"SKILL","subcategory":"","text":"innovative Services","sentiment":{"score":0.0,"label":null},"relevance":0.0,"mentions":[{"text":"innovative Services","location":[2163,2182],"confidence":0.75}],"count":0,"confidence":0.75,"usefulness":false,"Metadata":null},{"type":"SKILL","subcategory":"","text":"security","sentiment":{"score":0.0,"label":null},"relevance":0.0,"mentions":[{"text":"security","location":[2254,2262],"confidence":0.88},{"text":"security","location":[10346,10354],"confidence":0.89},{"text":"security","location":[17342,17350],"confidence":0.92},{"text":"security","location":[17729,17737],"confidence":0.93}],"count":3,"confidence":0.90250003,"usefulness":false,"Metadata":null},{"type":"SKILL","subcategory":"","text":"communication service","sentiment":{"score":0.0,"label":null},"relevance":0.0,"mentions":[{"text":"communication service","location":[2517,2538],"confidence":0.69}],"count":0,"confidence":0.69,"usefulness":false,"Metadata":null},{"type":"SKILL","subcategory":"","text":"marketing","sentiment":{"score":0.0,"label":null},"relevance":0.0,"mentions":[{"text":"marketing","location":[3665,3674],"confidence":0.98}],"count":0,"confidence":0.98,"usefulness":false,"Metadata":null},{"type":"SKILL","subcategory":"","text":"Cloud Chats","sentiment":{"score":0.0,"label":null},"relevance":0.0,"mentions":[{"text":"Cloud Chats","location":[3730,3741],"confidence":0.81}],"count":0,"confidence":0.81,"usefulness":false,"Metadata":null},{"type":"SKILL","subcategory":"","text":"cloud","sentiment":{"score":0.0,"label":null},"relevance":0.0,"mentions":[{"text":"cloud","location":[3759,3764],"confidence":0.55},{"text":"cloud","location":[4737,4742],"confidence":0.7},{"text":"cloud","location":[5667,5672],"confidence":0.77},{"text":"cloud","location":[7366,7371],"confidence":0.9},{"text":"cloud","location":[9885,9890],"confidence":0.55},{"text":"cloud","location":[9942,9947],"confidence":0.58},{"text":"cloud","location":[19994,19999],"confidence":0.64},{"text":"cloud storage","location":[10084,10097],"confidence":0.97},{"text":"cloud chats","location":[11160,11171],"confidence":0.66},{"text":"cloud service","location":[12220,12233],"confidence":0.84}],"count":6,"confidence":0.61375,"usefulness":false,"Metadata":null},{"type":"SKILL","subcategory":"","text":"backups","sentiment":{"score":0.0,"label":null},"relevance":0.0,"mentions":[{"text":"backups","location":[3963,3970],"confidence":0.54},{"text":"backups","location":[10073,10080],"confidence":0.7}],"count":1,"confidence":0.62,"usefulness":false,"Metadata":null},{"type":"SKILL","subcategory":"","text":"user data","sentiment":{"score":0.0,"label":null},"relevance":0.0,"mentions":[{"text":"user data","location":[4183,4192],"confidence":0.73}],"count":0,"confidence":0.73,"usefulness":false,"Metadata":null},{"type":"SKILL","subcategory":"","text":"encryption","sentiment":{"score":0.0,"label":null},"relevance":0.0,"mentions":[{"text":"encryption","location":[4246,4256],"confidence":0.99},{"text":"encryption","location":[17287,17297],"confidence":1.0}],"count":1,"confidence":0.995,"usefulness":false,"Metadata":null},{"type":"SKILL","subcategory":"","text":"Media","sentiment":{"score":0.0,"label":null},"relevance":0.0,"mentions":[{"text":"Media","location":[4831,4836],"confidence":0.82},{"text":"Media","location":[21249,21254],"confidence":0.7}],"count":1,"confidence":0.76,"usefulness":false,"Metadata":null},{"type":"SKILL","subcategory":"","text":"encrypted","sentiment":{"score":0.0,"label":null},"relevance":0.0,"mentions":[{"text":"encrypted","location":[4948,4957],"confidence":0.62},{"text":"encrypted","location":[5046,5055],"confidence":0.81},{"text":"encrypted","location":[9139,9148],"confidence":0.58},{"text":"encrypted data","location":[9248,9262],"confidence":0.47}],"count":1,"confidence":0.6,"usefulness":false,"Metadata":null},{"type":"SKILL","subcategory":"","text":"decipher","sentiment":{"score":0.0,"label":null},"relevance":0.0,"mentions":[{"text":"decipher","location":[5157,5165],"confidence":0.94}],"count":0,"confidence":0.94,"usefulness":false,"Metadata":null},{"type":"SKILL","subcategory":"","text":"purge","sentiment":{"score":0.0,"label":null},"relevance":0.0,"mentions":[{"text":"purge","location":[5471,5476],"confidence":0.53}],"count":0,"confidence":0.53,"usefulness":false,"Metadata":null},{"type":"SKILL","subcategory":"","text":"syncing","sentiment":{"score":0.0,"label":null},"relevance":0.0,"mentions":[{"text":"syncing","location":[6104,6111],"confidence":0.63},{"text":"syncing","location":[6776,6783],"confidence":0.79}],"count":0,"confidence":0.63,"usefulness":false,"Metadata":null},{"type":"SKILL","subcategory":"","text":"automatic","sentiment":{"score":0.0,"label":null},"relevance":0.0,"mentions":[{"text":"automatic","location":[6408,6417],"confidence":0.51}],"count":0,"confidence":0.51,"usefulness":false,"Metadata":null},{"type":"SKILL","subcategory":"","text":"algorithms","sentiment":{"score":0.0,"label":null},"relevance":0.0,"mentions":[{"text":"algorithms","location":[6418,6428],"confidence":0.62},{"text":"automated algorithms","location":[11116,11136],"confidence":0.97}],"count":0,"confidence":0.62,"usefulness":false,"Metadata":null},{"type":"SKILL","subcategory":"","text":"statistics","sentiment":{"score":0.0,"label":null},"relevance":0.0,"mentions":[{"text":"statistics","location":[6651,6661],"confidence":0.99}],"count":0,"confidence":0.99,"usefulness":false,"Metadata":null},{"type":"SKILL","subcategory":"","text":"Data","sentiment":{"score":0.0,"label":null},"relevance":0.0,"mentions":[{"text":"Data","location":[7270,7274],"confidence":0.49},{"text":"Data","location":[8283,8287],"confidence":0.58},{"text":"Data","location":[9844,9848],"confidence":0.69},{"text":"Data","location":[12665,12669],"confidence":0.97},{"text":"Data","location":[13011,13015],"confidence":0.74},{"text":"Location Data","location":[22358,22371],"confidence":0.81}],"count":3,"confidence":0.59000003,"usefulness":false,"Metadata":null},{"type":"SKILL","subcategory":"","text":"Cookies","sentiment":{"score":0.0,"label":null},"relevance":0.0,"mentions":[{"text":"Cookies","location":[7693,7700],"confidence":0.9}],"count":0,"confidence":0.9,"usefulness":false,"Metadata":null},{"type":"SKILL","subcategory":"","text":"Services","sentiment":{"score":0.0,"label":null},"relevance":0.0,"mentions":[{"text":"Services","location":[7765,7773],"confidence":0.79},{"text":"Services","location":[9805,9813],"confidence":0.59},{"text":"Services","location":[9859,9867],"confidence":0.55},{"text":"innovative Services","location":[2163,2182],"confidence":0.75},{"text":"Payment Services","location":[14487,14503],"confidence":0.87}],"count":2,"confidence":0.69,"usefulness":false,"Metadata":null},{"type":"SKILL","subcategory":"","text":"web","sentiment":{"score":0.0,"label":null},"relevance":0.0,"mentions":[{"text":"web","location":[7781,7784],"confidence":0.86},{"text":"web browser","location":[8155,8166],"confidence":0.68}],"count":0,"confidence":0.86,"usefulness":false,"Metadata":null},{"type":"SKILL","subcategory":"","text":"cookies","sentiment":{"score":0.0,"label":null},"relevance":0.0,"mentions":[{"text":"cookies","location":[7800,7807],"confidence":0.89},{"text":"cookies","location":[8040,8047],"confidence":0.73}],"count":0,"confidence":0.89,"usefulness":false,"Metadata":null},{"type":"SKILL","subcategory":"","text":"profiling","sentiment":{"score":0.0,"label":null},"relevance":0.0,"mentions":[{"text":"profiling","location":[7812,7821],"confidence":1.0}],"count":0,"confidence":1.0,"usefulness":false,"Metadata":null},{"type":"SKILL","subcategory":"","text":"advertising","sentiment":{"score":0.0,"label":null},"relevance":0.0,"mentions":[{"text":"advertising","location":[7825,7836],"confidence":0.98}],"count":0,"confidence":0.98,"usefulness":false,"Metadata":null},{"type":"SKILL","subcategory":"","text":"user experience","sentiment":{"score":0.0,"label":null},"relevance":0.0,"mentions":[{"text":"user experience","location":[7976,7991],"confidence":0.86}],"count":0,"confidence":0.86,"usefulness":false,"Metadata":null},{"type":"SKILL","subcategory":"","text":"web browser","sentiment":{"score":0.0,"label":null},"relevance":0.0,"mentions":[{"text":"web browser","location":[8155,8166],"confidence":0.68}],"count":0,"confidence":0.68,"usefulness":false,"Metadata":null},{"type":"SKILL","subcategory":"","text":"networks","sentiment":{"score":0.0,"label":null},"relevance":0.0,"mentions":[{"text":"networks","location":[8538,8546],"confidence":0.94}],"count":0,"confidence":0.94,"usefulness":false,"Metadata":null},{"type":"SKILL","subcategory":"","text":"media","sentiment":{"score":0.0,"label":null},"relevance":0.0,"mentions":[{"text":"media","location":[8876,8881],"confidence":0.82},{"text":"media","location":[9982,9987],"confidence":0.74},{"text":"media","location":[19710,19715],"confidence":0.85},{"text":"media","location":[21546,21551],"confidence":0.66}],"count":3,"confidence":0.815,"usefulness":false,"Metadata":null},{"type":"SKILL","subcategory":"","text":"encrypted data","sentiment":{"score":0.0,"label":null},"relevance":0.0,"mentions":[{"text":"encrypted data","location":[9248,9262],"confidence":0.47}],"count":0,"confidence":0.47,"usefulness":false,"Metadata":null},{"type":"SKILL","subcategory":"","text":"deliver","sentiment":{"score":0.0,"label":null},"relevance":0.0,"mentions":[{"text":"deliver","location":[9929,9936],"confidence":0.51}],"count":0,"confidence":0.51,"usefulness":false,"Metadata":null},{"type":"SKILL","subcategory":"","text":"cloud storage","sentiment":{"score":0.0,"label":null},"relevance":0.0,"mentions":[{"text":"cloud storage","location":[10084,10097],"confidence":0.97}],"count":0,"confidence":0.97,"usefulness":false,"Metadata":null},{"type":"SKILL","subcategory":"","text":"metadata","sentiment":{"score":0.0,"label":null},"relevance":0.0,"mentions":[{"text":"metadata","location":[10594,10602],"confidence":0.68}],"count":0,"confidence":0.68,"usefulness":false,"Metadata":null},{"type":"SKILL","subcategory":"","text":"phishing","sentiment":{"score":0.0,"label":null},"relevance":0.0,"mentions":[{"text":"phishing","location":[10673,10681],"confidence":0.85}],"count":0,"confidence":0.85,"usefulness":false,"Metadata":null},{"type":"SKILL","subcategory":"","text":"automated algorithms","sentiment":{"score":0.0,"label":null},"relevance":0.0,"mentions":[{"text":"automated algorithms","location":[11116,11136],"confidence":0.97}],"count":0,"confidence":0.97,"usefulness":false,"Metadata":null},{"type":"SKILL","subcategory":"","text":"analyze","sentiment":{"score":0.0,"label":null},"relevance":0.0,"mentions":[{"text":"analyze","location":[11140,11147],"confidence":0.99}],"count":0,"confidence":0.99,"usefulness":false,"Metadata":null},{"type":"SKILL","subcategory":"","text":"cloud chats","sentiment":{"score":0.0,"label":null},"relevance":0.0,"mentions":[{"text":"cloud chats","location":[11160,11171],"confidence":0.66}],"count":0,"confidence":0.66,"usefulness":false,"Metadata":null},{"type":"SKILL","subcategory":"","text":"calculate","sentiment":{"score":0.0,"label":null},"relevance":0.0,"mentions":[{"text":"calculate","location":[11631,11640],"confidence":0.84}],"count":0,"confidence":0.84,"usefulness":false,"Metadata":null},{"type":"SKILL","subcategory":"","text":"inline bots","sentiment":{"score":0.0,"label":null},"relevance":0.0,"mentions":[{"text":"inline bots","location":[11733,11744],"confidence":0.94}],"count":0,"confidence":0.94,"usefulness":false,"Metadata":null},{"type":"SKILL","subcategory":"","text":"bots","sentiment":{"score":0.0,"label":null},"relevance":0.0,"mentions":[{"text":"bots","location":[11777,11781],"confidence":0.69},{"text":"bots","location":[12970,12974],"confidence":0.84},{"text":"inline bots","location":[11733,11744],"confidence":0.94}],"count":0,"confidence":0.69,"usefulness":false,"Metadata":null},{"type":"SKILL","subcategory":"","text":"ad targeting","sentiment":{"score":0.0,"label":null},"relevance":0.0,"mentions":[{"text":"ad targeting","location":[12090,12102],"confidence":1.0}],"count":0,"confidence":1.0,"usefulness":false,"Metadata":null},{"type":"SKILL","subcategory":"","text":"cloud service","sentiment":{"score":0.0,"label":null},"relevance":0.0,"mentions":[{"text":"cloud service","location":[12220,12233],"confidence":0.84}],"count":0,"confidence":0.84,"usefulness":false,"Metadata":null},{"type":"SKILL","subcategory":"","text":"API","sentiment":{"score":0.0,"label":null},"relevance":0.0,"mentions":[{"text":"API","location":[12287,12290],"confidence":1.0}],"count":0,"confidence":1.0,"usefulness":false,"Metadata":null},{"type":"SKILL","subcategory":"","text":"Bots","sentiment":{"score":0.0,"label":null},"relevance":0.0,"mentions":[{"text":"Bots","location":[12342,12346],"confidence":0.6},{"text":"Bots","location":[13290,13294],"confidence":0.86}],"count":0,"confidence":0.6,"usefulness":false,"Metadata":null},{"type":"SKILL","subcategory":"","text":"bot","sentiment":{"score":0.0,"label":null},"relevance":0.0,"mentions":[{"text":"bot","location":[12797,12800],"confidence":0.71},{"text":"bot","location":[12871,12874],"confidence":0.95},{"text":"bot","location":[12923,12926],"confidence":0.9},{"text":"bot","location":[13800,13803],"confidence":0.69},{"text":"bot","location":[14021,14024],"confidence":0.83},{"text":"inline bots","location":[11733,11744],"confidence":0.94},{"text":"inline bot","location":[12819,12829],"confidence":0.99},{"text":"inline bot","location":[13894,13904],"confidence":0.99}],"count":2,"confidence":0.7,"usefulness":false,"Metadata":null},{"type":"SKILL","subcategory":"","text":"inline bot","sentiment":{"score":0.0,"label":null},"relevance":0.0,"mentions":[{"text":"inline bot","location":[12819,12829],"confidence":0.99},{"text":"inline bot","location":[13894,13904],"confidence":0.99}],"count":1,"confidence":0.99,"usefulness":false,"Metadata":null},{"type":"SKILL","subcategory":"","text":"website","sentiment":{"score":0.0,"label":null},"relevance":0.0,"mentions":[{"text":"website","location":[13492,13499],"confidence":0.83}],"count":0,"confidence":0.83,"usefulness":false,"Metadata":null},{"type":"SKILL","subcategory":"","text":"query","sentiment":{"score":0.0,"label":null},"relevance":0.0,"mentions":[{"text":"query","location":[13755,13760],"confidence":0.91},{"text":"query","location":[13779,13784],"confidence":0.96}],"count":0,"confidence":0.91,"usefulness":false,"Metadata":null},{"type":"SKILL","subcategory":"","text":"service","sentiment":{"score":0.0,"label":null},"relevance":0.0,"mentions":[{"text":"service","location":[13831,13838],"confidence":0.71},{"text":"messaging services","location":[277,295],"confidence":0.72},{"text":"communication service","location":[2517,2538],"confidence":0.69},{"text":"cloud service","location":[12220,12233],"confidence":0.84}],"count":0,"confidence":0.71,"usefulness":false,"Metadata":null},{"type":"SKILL","subcategory":"","text":"Payment Services","sentiment":{"score":0.0,"label":null},"relevance":0.0,"mentions":[{"text":"Payment Services","location":[14487,14503],"confidence":0.87}],"count":0,"confidence":0.87,"usefulness":false,"Metadata":null},{"type":"SKILL","subcategory":"","text":"Payment","sentiment":{"score":0.0,"label":null},"relevance":0.0,"mentions":[{"text":"Payment","location":[14537,14544],"confidence":0.6},{"text":"Payment Services","location":[14487,14503],"confidence":0.87}],"count":0,"confidence":0.6,"usefulness":false,"Metadata":null},{"type":"SKILL","subcategory":"","text":"privacy","sentiment":{"score":0.0,"label":null},"relevance":0.0,"mentions":[{"text":"privacy","location":[15011,15018],"confidence":0.83}],"count":0,"confidence":0.83,"usefulness":false,"Metadata":null},{"type":"SKILL","subcategory":"","text":"communicate","sentiment":{"score":0.0,"label":null},"relevance":0.0,"mentions":[{"text":"communicate","location":[16891,16902],"confidence":0.98},{"text":"communicate","location":[17039,17050],"confidence":0.97}],"count":0,"confidence":0.98,"usefulness":false,"Metadata":null},{"type":"SKILL","subcategory":"","text":"technical","sentiment":{"score":0.0,"label":null},"relevance":0.0,"mentions":[{"text":"technical","location":[17238,17247],"confidence":0.78}],"count":0,"confidence":0.78,"usefulness":false,"Metadata":null},{"type":"SKILL","subcategory":"","text":"organizational","sentiment":{"score":0.0,"label":null},"relevance":0.0,"mentions":[{"text":"organizational","location":[17252,17266],"confidence":0.52}],"count":0,"confidence":0.52,"usefulness":false,"Metadata":null},{"type":"SKILL","subcategory":"","text":"support","sentiment":{"score":0.0,"label":null},"relevance":0.0,"mentions":[{"text":"support","location":[17651,17658],"confidence":0.61}],"count":0,"confidence":0.61,"usefulness":false,"Metadata":null},{"type":"SKILL","subcategory":"","text":"integrity","sentiment":{"score":0.0,"label":null},"relevance":0.0,"mentions":[{"text":"integrity","location":[17742,17751],"confidence":0.79}],"count":0,"confidence":0.79,"usefulness":false,"Metadata":null},{"type":"SKILL","subcategory":"","text":"Law Enforcement","sentiment":{"score":0.0,"label":null},"relevance":0.0,"mentions":[{"text":"Law Enforcement","location":[18048,18063],"confidence":0.65}],"count":0,"confidence":0.65,"usefulness":false,"Metadata":null},{"type":"SKILL","subcategory":"","text":"mobile apps","sentiment":{"score":0.0,"label":null},"relevance":0.0,"mentions":[{"text":"mobile apps","location":[19319,19330],"confidence":0.8}],"count":0,"confidence":0.8,"usefulness":false,"Metadata":null},{"type":"SKILL","subcategory":"","text":"Location Data","sentiment":{"score":0.0,"label":null},"relevance":0.0,"mentions":[{"text":"Location Data","location":[22358,22371],"confidence":0.81}],"count":0,"confidence":0.81,"usefulness":false,"Metadata":null},{"type":"SKILL","subcategory":"","text":"open source","sentiment":{"score":0.0,"label":null},"relevance":0.0,"mentions":[{"text":"open source","location":[22836,22847],"confidence":0.75}],"count":0,"confidence":0.75,"usefulness":false,"Metadata":null},{"type":"SKILL","subcategory":"","text":"examine","sentiment":{"score":0.0,"label":null},"relevance":0.0,"mentions":[{"text":"examine","location":[22865,22872],"confidence":0.65}],"count":0,"confidence":0.65,"usefulness":false,"Metadata":null},{"type":"SKILL","subcategory":"","text":"Protocol","sentiment":{"score":0.0,"label":null},"relevance":0.0,"mentions":[{"text":"Protocol","location":[23003,23011],"confidence":0.53}],"count":0,"confidence":0.53,"usefulness":false,"Metadata":null},{"type":"URL","subcategory":"","text":"https://telegram.org/tos.","sentiment":{"score":0.0,"label":null},"relevance":0.0,"mentions":[{"text":"https://telegram.org/tos.","location":[896,921],"confidence":0.8}],"count":0,"confidence":0.8,"usefulness":false,"Metadata":null},{"type":"URL","subcategory":"","text":"https://t.me/transparency.","sentiment":{"score":0.0,"label":null},"relevance":0.0,"mentions":[{"text":"https://t.me/transparency.","location":[18347,18373],"confidence":0.8}],"count":0,"confidence":0.8,"usefulness":false,"Metadata":null},{"type":"URL","subcategory":"","text":"www.telegram.org/privacy.","sentiment":{"score":0.0,"label":null},"relevance":0.0,"mentions":[{"text":"www.telegram.org/privacy.","location":[21947,21972],"confidence":0.8}],"count":0,"confidence":0.8,"usefulness":false,"Metadata":null},{"type":"URL","subcategory":"","text":"https://core.telegram.org/api","sentiment":{"score":0.0,"label":null},"relevance":0.0,"mentions":[{"text":"https://core.telegram.org/api","location":[22913,22942],"confidence":0.8}],"count":0,"confidence":0.8,"usefulness":false,"Metadata":null},{"type":"URL","subcategory":"","text":"https://core.telegram.org/bots","sentiment":{"score":0.0,"label":null},"relevance":0.0,"mentions":[{"text":"https://core.telegram.org/bots","location":[22966,22996],"confidence":0.8}],"count":0,"confidence":0.8,"usefulness":false,"Metadata":null},{"type":"URL","subcategory":"","text":"https://core.telegram.org/mtproto","sentiment":{"score":0.0,"label":null},"relevance":0.0,"mentions":[{"text":"https://core.telegram.org/mtproto","location":[23016,23049],"confidence":0.8}],"count":0,"confidence":0.8,"usefulness":false,"Metadata":null},{"type":"URL","subcategory":"","text":"https://telegram.org/apps#source-code.","sentiment":{"score":0.0,"label":null},"relevance":0.0,"mentions":[{"text":"https://telegram.org/apps#source-code.","location":[23076,23114],"confidence":0.8}],"count":0,"confidence":0.8,"usefulness":false,"Metadata":null}]}