{"usage":null,"language":"de","entities":[{"type":"DATE","subcategory":null,"text":"27. April 2016","sentiment":{"score":0.0,"label":null},"relevance":0.0,"mentions":[{"text":"27. April 2016","location":[37800,37814],"confidence":0.0}],"count":0,"confidence":0.0,"usefulness":false,"Metadata":{"day":"27","year":"2016","month":"4"}},{"type":"EMAILADDRESS","subcategory":null,"text":"info@xing.com","sentiment":{"score":0.0,"label":"neutral"},"relevance":0.091855,"mentions":[{"text":"info@xing.com","location":[2347,2360],"confidence":0.8}],"count":1,"confidence":0.8,"usefulness":false,"Metadata":null},{"type":"EMAILADDRESS","subcategory":null,"text":"Datenschutzbeauftragter@xing.com","sentiment":{"score":0.0,"label":"neutral"},"relevance":0.085483,"mentions":[{"text":"Datenschutzbeauftragter@xing.com","location":[2491,2523],"confidence":0.8}],"count":1,"confidence":0.8,"usefulness":false,"Metadata":null},{"type":"EVENT","subcategory":null,"text":"Vertragsabschluss","sentiment":{"score":0.0,"label":null},"relevance":0.0005341576,"mentions":[{"text":"Vertragsabschluss","location":[3037,3054],"confidence":0.0}],"count":0,"confidence":0.0,"usefulness":false,"Metadata":{}},{"type":"EVENT","subcategory":null,"text":"Events","sentiment":{"score":0.0,"label":null},"relevance":0.004000303,"mentions":[{"text":"Events","location":[5326,5332],"confidence":0.0},{"text":"Events","location":[7452,7458],"confidence":0.0}],"count":0,"confidence":0.0,"usefulness":false,"Metadata":{}},{"type":"EVENT","subcategory":null,"text":"Veranstaltungen","sentiment":{"score":0.0,"label":null},"relevance":0.001210019,"mentions":[{"text":"Veranstaltungen","location":[7397,7412],"confidence":0.0},{"text":"Veranstaltungen","location":[12427,12442],"confidence":0.0}],"count":1,"confidence":0.0,"usefulness":false,"Metadata":{}},{"type":"EVENT","subcategory":null,"text":"Seminare","sentiment":{"score":0.0,"label":null},"relevance":0.0003490736,"mentions":[{"text":"Seminare","location":[7463,7471],"confidence":0.0}],"count":0,"confidence":0.0,"usefulness":false,"Metadata":{}},{"type":"EVENT","subcategory":null,"text":"Veranstaltung","sentiment":{"score":0.0,"label":null},"relevance":0.0019038502,"mentions":[{"text":"Veranstaltung","location":[12535,12548],"confidence":0.0},{"text":"Veranstaltung","location":[12800,12813],"confidence":0.0},{"text":"Veranstaltung","location":[13202,13215],"confidence":0.0}],"count":0,"confidence":0.0,"usefulness":false,"Metadata":{}},{"type":"EVENT","subcategory":null,"text":"Sitzung","sentiment":{"score":0.0,"label":null},"relevance":0.0005360817,"mentions":[{"text":"Sitzung","location":[24592,24599],"confidence":0.0}],"count":0,"confidence":0.0,"usefulness":false,"Metadata":{}},{"type":"LOCATION","subcategory":null,"text":"Hamburg","sentiment":{"score":0.0,"label":null},"relevance":0.00017010892,"mentions":[{"text":"Hamburg","location":[2269,2276],"confidence":0.0},{"text":"Hamburg","location":[2461,2468],"confidence":0.0}],"count":0,"confidence":0.0,"usefulness":false,"Metadata":{"wikipedia_url":"https://en.wikipedia.org/wiki/Hamburg","mid":"/m/03hrz"}},{"type":"LOCATION","subcategory":null,"text":"Deutschland","sentiment":{"score":0.0,"label":null},"relevance":0.00017010892,"mentions":[{"text":"Deutschland","location":[2278,2289],"confidence":0.0},{"text":"Deutschland","location":[2470,2481],"confidence":0.0}],"count":0,"confidence":0.0,"usefulness":false,"Metadata":{"wikipedia_url":"https://en.wikipedia.org/wiki/Germany","mid":"/m/0345h"}},{"type":"LOCATION","subcategory":null,"text":"Land","sentiment":{"score":0.0,"label":null},"relevance":0.0004815535,"mentions":[{"text":"Land","location":[10809,10813],"confidence":0.0}],"count":1,"confidence":0.0,"usefulness":false,"Metadata":{}},{"type":"LOCATION","subcategory":null,"text":"Stadt","sentiment":{"score":0.0,"label":null},"relevance":0.00056548155,"mentions":[{"text":"Stadt","location":[10799,10804],"confidence":0.0}],"count":0,"confidence":0.0,"usefulness":false,"Metadata":{}},{"type":"LOCATION","subcategory":null,"text":"Drittländern","sentiment":{"score":0.0,"label":null},"relevance":0.0012237666,"mentions":[{"text":"Drittländern","location":[26441,26453],"confidence":0.0},{"text":"Drittländern","location":[30950,30962],"confidence":0.0}],"count":1,"confidence":0.0,"usefulness":false,"Metadata":{}},{"type":"LOCATION","subcategory":null,"text":"Städten","sentiment":{"score":0.0,"label":null},"relevance":0.0005298378,"mentions":[{"text":"Städten","location":[25275,25282],"confidence":0.0}],"count":0,"confidence":0.0,"usefulness":false,"Metadata":{}},{"type":"NUMBER","subcategory":null,"text":"30","sentiment":{"score":0.0,"label":null},"relevance":0.0,"mentions":[{"text":"30","location":[2259,2261],"confidence":0.0},{"text":"30","location":[2451,2453],"confidence":0.0}],"count":0,"confidence":0.0,"usefulness":false,"Metadata":{"value":"30"}},{"type":"NUMBER","subcategory":null,"text":"20354","sentiment":{"score":0.0,"label":null},"relevance":0.0,"mentions":[{"text":"20354","location":[2455,2460],"confidence":0.0}],"count":0,"confidence":0.0,"usefulness":false,"Metadata":{"value":"20354"}},{"type":"NUMBER","subcategory":null,"text":"+49","sentiment":{"score":0.0,"label":null},"relevance":0.0,"mentions":[{"text":"+49","location":[2320,2323],"confidence":0.0}],"count":0,"confidence":0.0,"usefulness":false,"Metadata":{"value":"49"}},{"type":"NUMBER","subcategory":null,"text":"40","sentiment":{"score":0.0,"label":null},"relevance":0.0,"mentions":[{"text":"40","location":[2324,2326],"confidence":0.0}],"count":0,"confidence":0.0,"usefulness":false,"Metadata":{"value":"40"}},{"type":"NUMBER","subcategory":null,"text":"419","sentiment":{"score":0.0,"label":null},"relevance":0.0,"mentions":[{"text":"419","location":[2327,2330],"confidence":0.0}],"count":0,"confidence":0.0,"usefulness":false,"Metadata":{"value":"419"}},{"type":"NUMBER","subcategory":null,"text":"1","sentiment":{"score":0.0,"label":null},"relevance":0.0,"mentions":[{"text":"1","location":[2659,2660],"confidence":0.0},{"text":"1","location":[4018,4019],"confidence":0.0},{"text":"1","location":[36417,36418],"confidence":0.0},{"text":"1","location":[38037,38038],"confidence":0.0}],"count":3,"confidence":0.0,"usefulness":false,"Metadata":{"value":"1"}},{"type":"NUMBER","subcategory":null,"text":"1.001","sentiment":{"score":0.0,"label":null},"relevance":0.0,"mentions":[{"text":"1.001","location":[6255,6260],"confidence":0.0},{"text":"1.001","location":[6255,6260],"confidence":0.0}],"count":0,"confidence":0.0,"usefulness":false,"Metadata":{"value":"1.001000"}},{"type":"NUMBER","subcategory":null,"text":"2","sentiment":{"score":0.0,"label":null},"relevance":0.0,"mentions":[{"text":"2","location":[6300,6301],"confidence":0.0}],"count":1,"confidence":0.0,"usefulness":false,"Metadata":{"value":"2"}},{"type":"NUMBER","subcategory":null,"text":"3","sentiment":{"score":0.0,"label":null},"relevance":0.0,"mentions":[{"text":"3","location":[7762,7763],"confidence":0.0}],"count":0,"confidence":0.0,"usefulness":false,"Metadata":{"value":"3"}},{"type":"NUMBER","subcategory":null,"text":"6","sentiment":{"score":0.0,"label":null},"relevance":0.0,"mentions":[{"text":"6","location":[8799,8800],"confidence":0.0},{"text":"6","location":[25948,25949],"confidence":0.0},{"text":"6","location":[36410,36411],"confidence":0.0}],"count":10,"confidence":0.0,"usefulness":false,"Metadata":{"value":"6"}},{"type":"NUMBER","subcategory":null,"text":"32","sentiment":{"score":0.0,"label":null},"relevance":0.0,"mentions":[{"text":"32","location":[8824,8826],"confidence":0.0}],"count":0,"confidence":0.0,"usefulness":false,"Metadata":{"value":"32"}},{"type":"NUMBER","subcategory":null,"text":"4","sentiment":{"score":0.0,"label":null},"relevance":0.0,"mentions":[{"text":"4","location":[10007,10008],"confidence":0.0},{"text":"4","location":[38028,38029],"confidence":0.0},{"text":"4","location":[39334,39335],"confidence":0.0},{"text":"4","location":[39343,39344],"confidence":0.0}],"count":3,"confidence":0.0,"usefulness":false,"Metadata":{"value":"4"}},{"type":"NUMBER","subcategory":null,"text":"5","sentiment":{"score":0.0,"label":null},"relevance":0.0,"mentions":[{"text":"5","location":[13881,13882],"confidence":0.0}],"count":0,"confidence":0.0,"usefulness":false,"Metadata":{"value":"5"}},{"type":"NUMBER","subcategory":null,"text":"45","sentiment":{"score":0.0,"label":null},"relevance":0.0,"mentions":[{"text":"45","location":[17172,17174],"confidence":0.0},{"text":"45","location":[17636,17638],"confidence":0.0}],"count":0,"confidence":0.0,"usefulness":false,"Metadata":{"value":"45"}},{"type":"NUMBER","subcategory":null,"text":"46","sentiment":{"score":0.0,"label":null},"relevance":0.0,"mentions":[{"text":"46","location":[17219,17221],"confidence":0.0},{"text":"46","location":[17683,17685],"confidence":0.0},{"text":"46","location":[17890,17892],"confidence":0.0}],"count":0,"confidence":0.0,"usefulness":false,"Metadata":{"value":"46"}},{"type":"NUMBER","subcategory":null,"text":"27","sentiment":{"score":0.0,"label":null},"relevance":0.0,"mentions":[{"text":"27","location":[37800,37802],"confidence":0.0}],"count":0,"confidence":0.0,"usefulness":false,"Metadata":{"value":"27"}},{"type":"NUMBER","subcategory":null,"text":"2016","sentiment":{"score":0.0,"label":null},"relevance":0.0,"mentions":[{"text":"2016","location":[37810,37814],"confidence":0.0}],"count":0,"confidence":0.0,"usefulness":false,"Metadata":{"value":"2016"}},{"type":"ORGANIZATION","subcategory":null,"text":"XING","sentiment":{"score":0.0,"label":null},"relevance":0.004951865,"mentions":[{"text":"XING","location":[0,4],"confidence":0.0},{"text":"XING","location":[61,65],"confidence":0.0},{"text":"XING","location":[502,506],"confidence":0.0},{"text":"XING","location":[649,653],"confidence":0.0},{"text":"XING","location":[953,957],"confidence":0.0},{"text":"XING","location":[1190,1194],"confidence":0.0},{"text":"XING","location":[1430,1434],"confidence":0.0},{"text":"XING","location":[1704,1708],"confidence":0.0},{"text":"XING","location":[4103,4107],"confidence":0.0},{"text":"XING","location":[7036,7040],"confidence":0.0},{"text":"XING","location":[7806,7810],"confidence":0.0},{"text":"XING","location":[7856,7860],"confidence":0.0},{"text":"XING","location":[8540,8544],"confidence":0.0},{"text":"XING","location":[9976,9980],"confidence":0.0},{"text":"XING","location":[11102,11106],"confidence":0.0},{"text":"XING","location":[11582,11586],"confidence":0.0},{"text":"XING","location":[12964,12968],"confidence":0.0},{"text":"XING","location":[13285,13289],"confidence":0.0},{"text":"XING","location":[15465,15469],"confidence":0.0},{"text":"XING","location":[15826,15830],"confidence":0.0},{"text":"XING","location":[15955,15959],"confidence":0.0},{"text":"XING","location":[18672,18676],"confidence":0.0},{"text":"XING","location":[18922,18926],"confidence":0.0},{"text":"XING","location":[19513,19517],"confidence":0.0},{"text":"XING","location":[19590,19594],"confidence":0.0},{"text":"XING","location":[21032,21036],"confidence":0.0},{"text":"XING","location":[21072,21076],"confidence":0.0},{"text":"XING","location":[21115,21119],"confidence":0.0},{"text":"XING","location":[21494,21498],"confidence":0.0},{"text":"XING","location":[22616,22620],"confidence":0.0},{"text":"XING","location":[24460,24464],"confidence":0.0},{"text":"XING","location":[24658,24662],"confidence":0.0},{"text":"XING","location":[27012,27016],"confidence":0.0},{"text":"XING","location":[27108,27112],"confidence":0.0},{"text":"XING","location":[27218,27222],"confidence":0.0},{"text":"XING","location":[29015,29019],"confidence":0.0},{"text":"XING","location":[30020,30024],"confidence":0.0},{"text":"XING","location":[30069,30073],"confidence":0.0},{"text":"XING","location":[30109,30113],"confidence":0.0},{"text":"XING","location":[32350,32354],"confidence":0.0},{"text":"XING","location":[33506,33510],"confidence":0.0},{"text":"XING","location":[34177,34181],"confidence":0.0},{"text":"XING","location":[34974,34978],"confidence":0.0},{"text":"XING","location":[35084,35088],"confidence":0.0},{"text":"XING","location":[35236,35240],"confidence":0.0},{"text":"XING","location":[35305,35309],"confidence":0.0},{"text":"XING","location":[35448,35452],"confidence":0.0},{"text":"XING","location":[35635,35639],"confidence":0.0},{"text":"XING","location":[35668,35672],"confidence":0.0},{"text":"XING","location":[35794,35798],"confidence":0.0},{"text":"XING","location":[35827,35831],"confidence":0.0},{"text":"XING","location":[37447,37451],"confidence":0.0},{"text":"XING","location":[37464,37468],"confidence":0.0},{"text":"XING","location":[37488,37492],"confidence":0.0},{"text":"XING","location":[37686,37690],"confidence":0.0},{"text":"XING","location":[38656,38660],"confidence":0.0}],"count":53,"confidence":0.0,"usefulness":false,"Metadata":{"mid":"/m/083092","wikipedia_url":"https://en.wikipedia.org/wiki/XING"}},{"type":"ORGANIZATION","subcategory":null,"text":"EU","sentiment":{"score":0.0,"label":null},"relevance":0.0035128857,"mentions":[{"text":"EU","location":[2088,2090],"confidence":0.0},{"text":"EU","location":[8827,8829],"confidence":0.0},{"text":"EU","location":[9095,9097],"confidence":0.0},{"text":"EU","location":[9487,9489],"confidence":0.0},{"text":"EU","location":[12395,12397],"confidence":0.0},{"text":"EU","location":[13870,13872],"confidence":0.0},{"text":"EU","location":[17175,17177],"confidence":0.0},{"text":"EU","location":[17222,17224],"confidence":0.0},{"text":"EU","location":[17639,17641],"confidence":0.0},{"text":"EU","location":[17686,17688],"confidence":0.0},{"text":"EU","location":[17801,17803],"confidence":0.0},{"text":"EU","location":[17956,17958],"confidence":0.0},{"text":"EU","location":[17893,17895],"confidence":0.0},{"text":"EU","location":[25687,25689],"confidence":0.0},{"text":"EU","location":[26409,26411],"confidence":0.0},{"text":"EU","location":[26473,26475],"confidence":0.0},{"text":"EU","location":[30918,30920],"confidence":0.0},{"text":"EU","location":[30982,30984],"confidence":0.0},{"text":"EU","location":[31377,31379],"confidence":0.0},{"text":"EU","location":[37715,37717],"confidence":0.0},{"text":"EU","location":[37741,37743],"confidence":0.0},{"text":"EU","location":[40025,40027],"confidence":0.0},{"text":"EU","location":[38039,38041],"confidence":0.0}],"count":27,"confidence":0.0,"usefulness":false,"Metadata":{}},{"type":"ORGANIZATION","subcategory":null,"text":"DSGVO","sentiment":{"score":0.0,"label":null},"relevance":0.011704518,"mentions":[{"text":"DSGVO","location":[9098,9103],"confidence":0.0},{"text":"DSGVO","location":[12398,12403],"confidence":0.0},{"text":"DSGVO","location":[13674,13679],"confidence":0.0},{"text":"DSGVO","location":[13873,13878],"confidence":0.0},{"text":"DSGVO","location":[17689,17694],"confidence":0.0},{"text":"DSGVO","location":[25958,25963],"confidence":0.0},{"text":"DSGVO","location":[25690,25695],"confidence":0.0},{"text":"DSGVO","location":[36433,36438],"confidence":0.0},{"text":"DSGVO","location":[39348,39353],"confidence":0.0}],"count":7,"confidence":0.0,"usefulness":false,"Metadata":{}},{"type":"ORGANIZATION","subcategory":null,"text":"Google","sentiment":{"score":0.0,"label":null},"relevance":0.005227695,"mentions":[{"text":"Google","location":[9362,9368],"confidence":0.0},{"text":"Google","location":[26314,26320],"confidence":0.0},{"text":"Google","location":[28622,28628],"confidence":0.0},{"text":"Google","location":[31614,31620],"confidence":0.0},{"text":"Google","location":[31637,31643],"confidence":0.0}],"count":4,"confidence":0.0,"usefulness":false,"Metadata":{"wikipedia_url":"https://en.wikipedia.org/wiki/Google","mid":"/m/045c7b"}},{"type":"ORGANIZATION","subcategory":null,"text":"Twitter","sentiment":{"score":0.0,"label":null},"relevance":0.00017638129,"mentions":[{"text":"Twitter","location":[10815,10822],"confidence":0.0}],"count":0,"confidence":0.0,"usefulness":false,"Metadata":{}},{"type":"ORGANIZATION","subcategory":null,"text":"Europäischen Union","sentiment":{"score":0.0,"label":null},"relevance":0.00014667929,"mentions":[{"text":"Europäischen Union","location":[22290,22308],"confidence":0.0}],"count":0,"confidence":0.0,"usefulness":false,"Metadata":{"mid":"/m/0_6t_z8","wikipedia_url":"https://en.wikipedia.org/wiki/European_Union"}},{"type":"ORGANIZATION","subcategory":null,"text":"VWO","sentiment":{"score":0.0,"label":null},"relevance":0.00075588963,"mentions":[{"text":"VWO","location":[28326,28329],"confidence":0.0}],"count":0,"confidence":0.0,"usefulness":false,"Metadata":{}},{"type":"ORGANIZATION","subcategory":null,"text":"Adobe","sentiment":{"score":0.0,"label":null},"relevance":0.00060129404,"mentions":[{"text":"Adobe","location":[28256,28261],"confidence":0.0}],"count":0,"confidence":0.0,"usefulness":false,"Metadata":{"wikipedia_url":"https://en.wikipedia.org/wiki/Adobe_Inc.","mid":"/m/0vlf"}},{"type":"ORGANIZATION","subcategory":null,"text":"IBM","sentiment":{"score":0.0,"label":null},"relevance":0.00060129404,"mentions":[{"text":"IBM","location":[28306,28309],"confidence":0.0}],"count":0,"confidence":0.0,"usefulness":false,"Metadata":{"mid":"/m/03sc8","wikipedia_url":"https://en.wikipedia.org/wiki/IBM"}},{"type":"ORGANIZATION","subcategory":null,"text":"Microsoft","sentiment":{"score":0.0,"label":null},"relevance":0.0050377226,"mentions":[{"text":"Microsoft","location":[31668,31677],"confidence":0.0}],"count":0,"confidence":0.0,"usefulness":false,"Metadata":{"wikipedia_url":"https://en.wikipedia.org/wiki/Microsoft","mid":"/m/04sv4"}},{"type":"ORGANIZATION","subcategory":null,"text":"Aufsichtsbehörde","sentiment":{"score":0.0,"label":null},"relevance":0.0189933,"mentions":[{"text":"Aufsichtsbehörde","location":[37354,37370],"confidence":0.0}],"count":0,"confidence":0.0,"usefulness":false,"Metadata":{}},{"type":"ORGANIZATION","subcategory":null,"text":"New Work SE","sentiment":{"score":0.0,"label":"neutral"},"relevance":0.104672,"mentions":[{"text":"New Work SE","location":[2037,2048],"confidence":0.461464}],"count":1,"confidence":0.461464,"usefulness":false,"Metadata":null},{"type":"ORGANIZATION","subcategory":null,"text":"Facebook","sentiment":{"score":0.0,"label":"neutral"},"relevance":0.1405175,"mentions":[{"text":"Facebook","location":[31751,31759],"confidence":0.978621}],"count":2,"confidence":0.90436804,"usefulness":false,"Metadata":null},{"type":"ORGANIZATION","subcategory":null,"text":"Climate Partner","sentiment":{"score":0.0,"label":"neutral"},"relevance":0.140264,"mentions":[{"text":"Climate Partner","location":[16788,16803],"confidence":0.165821}],"count":1,"confidence":0.165821,"usefulness":false,"Metadata":null},{"type":"ORGANIZATION","subcategory":null,"text":"Europäischen Kommission","sentiment":{"score":0.0,"label":"neutral"},"relevance":0.156941,"mentions":[{"text":"Europäischen Kommission","location":[17766,17789],"confidence":0.487426},{"text":"Europäischen Kommission","location":[18019,18042],"confidence":0.558888}],"count":2,"confidence":0.523157,"usefulness":false,"Metadata":null},{"type":"ORGANIZATION","subcategory":null,"text":"Criteo","sentiment":{"score":0.0,"label":"neutral"},"relevance":0.580557,"mentions":[{"text":"Criteo","location":[31681,31687],"confidence":0.299391},{"text":"Criteo","location":[31704,31710],"confidence":0.576995}],"count":2,"confidence":0.703639,"usefulness":false,"Metadata":null},{"type":"ORGANIZATION","subcategory":null,"text":"ADITION","sentiment":{"score":-0.575591,"label":"negative"},"relevance":0.552895,"mentions":[{"text":"ADITION","location":[31953,31960],"confidence":0.74744}],"count":2,"confidence":0.928804,"usefulness":false,"Metadata":null},{"type":"ORGANIZATION","subcategory":null,"text":"Pinterest","sentiment":{"score":0.0,"label":"neutral"},"relevance":0.544565,"mentions":[{"text":"Pinterest","location":[32001,32010],"confidence":0.349659},{"text":"Pinterest","location":[32027,32036],"confidence":0.410202}],"count":2,"confidence":0.61643,"usefulness":false,"Metadata":null},{"type":"ORGANIZATION","subcategory":null,"text":"LinkedIn","sentiment":{"score":0.0,"label":"neutral"},"relevance":0.312347,"mentions":[{"text":"LinkedIn","location":[31739,31747],"confidence":0.696017}],"count":1,"confidence":0.696017,"usefulness":false,"Metadata":null},{"type":"ORGANIZATION","subcategory":null,"text":"Media","sentiment":{"score":0.0,"label":"neutral"},"relevance":0.30188,"mentions":[{"text":"Media","location":[31820,31825],"confidence":0.774279},{"text":"Performance Media","location":[31842,31859],"confidence":0.0}],"count":2,"confidence":0.86192,"usefulness":false,"Metadata":null},{"type":"ORGANIZATION","subcategory":null,"text":"Europäischen Parlaments","sentiment":{"score":0.0,"label":"neutral"},"relevance":0.241131,"mentions":[{"text":"Europäischen Parlaments","location":[37758,37781],"confidence":0.595927}],"count":1,"confidence":0.595927,"usefulness":false,"Metadata":null},{"type":"ORGANIZATION","subcategory":null,"text":"Rates","sentiment":{"score":0.0,"label":"neutral"},"relevance":0.238877,"mentions":[{"text":"Rates","location":[37790,37795],"confidence":0.661806}],"count":1,"confidence":0.661806,"usefulness":false,"Metadata":null},{"type":"ORGANIZATION","subcategory":null,"text":"Xandr","sentiment":null,"relevance":0.0,"mentions":[{"text":"Xandr","location":[29983,29988],"confidence":0.0}],"count":2,"confidence":0.81467074,"usefulness":false,"Metadata":null},{"type":"ORGANIZATION","subcategory":null,"text":"AdDefend","sentiment":null,"relevance":0.0,"mentions":[{"text":"AdDefend","location":[31796,31804],"confidence":0.0}],"count":0,"confidence":0.5964903,"usefulness":false,"Metadata":null},{"type":"ORGANIZATION","subcategory":null,"text":"Performance Media","sentiment":null,"relevance":0.0,"mentions":[{"text":"Performance Media","location":[31842,31859],"confidence":0.0}],"count":0,"confidence":0.61250097,"usefulness":false,"Metadata":null},{"type":"ORGANIZATION","subcategory":null,"text":"Adform","sentiment":null,"relevance":0.0,"mentions":[{"text":"Adform","location":[31863,31869],"confidence":0.0}],"count":0,"confidence":0.73127574,"usefulness":false,"Metadata":null},{"type":"ORGANIZATION","subcategory":null,"text":"kununu","sentiment":null,"relevance":0.0,"mentions":[{"text":"kununu","location":[33013,33019],"confidence":0.0}],"count":0,"confidence":0.7274052,"usefulness":false,"Metadata":null},{"type":"OTHER","subcategory":null,"text":"Datenschutzbeauftragter@xing.com","sentiment":{"score":0.0,"label":null},"relevance":0.0005177077,"mentions":[{"text":"Datenschutzbeauftragter@xing.com","location":[2491,2523],"confidence":0.0}],"count":0,"confidence":0.0,"usefulness":false,"Metadata":{"mid":"/g/11bwcd7471","wikipedia_url":"https://en.wikipedia.org/wiki/Data_protection_officer"}},{"type":"OTHER","subcategory":null,"text":"https://vwo.com/opt-out/","sentiment":{"score":0.0,"label":null},"relevance":0.0005263121,"mentions":[{"text":"https://vwo.com/opt-out/","location":[28478,28502],"confidence":0.0}],"count":0,"confidence":0.0,"usefulness":false,"Metadata":{}},{"type":"PERSON","subcategory":null,"text":"Felix Lasse","sentiment":{"score":0.0,"label":null},"relevance":0.00023914364,"mentions":[{"text":"Felix Lasse","location":[2424,2435],"confidence":0.0}],"count":0,"confidence":0.0,"usefulness":false,"Metadata":{}},{"type":"PERSON","subcategory":null,"text":"Bing","sentiment":{"score":0.0,"label":"neutral"},"relevance":0.192901,"mentions":[{"text":"Bing","location":[31647,31651],"confidence":0.710612}],"count":1,"confidence":0.710612,"usefulness":false,"Metadata":null},{"type":"QUANTITY","subcategory":null,"text":"1","sentiment":null,"relevance":0.0,"mentions":[{"text":"1","location":[4018,4019],"confidence":0.0}],"count":0,"confidence":0.7211324,"usefulness":false,"Metadata":null},{"type":"URL","subcategory":null,"text":"https://vwo.com/opt-out/","sentiment":{"score":0.0,"label":"neutral"},"relevance":0.186855,"mentions":[{"text":"https://vwo.com/opt-out/","location":[28478,28502],"confidence":0.8}],"count":1,"confidence":0.8,"usefulness":false,"Metadata":null}]}